Workbook

Sheet events-入力用
A1: country_iso3 | B1: country_name | C1: country_name_ja | D1: title | E1: summary | F1: background | G1: impact | H1: future | I1: detail | J1: 関係国１ | K1: 関係国２ | L1: 関係国３ | M1: related_country_1 | N1: related_country_2 | O1: related_country_3 | P1: related_countries | Q1: impact_summary | R1: category | S1: event_date | T1: source_name | U1: source_url | V1: importance
A2: =IF(C2="","",VLOOKUP(C2,[1]ISO辞書!A:C,2,FALSE)) -> SVN | B2: =IF(C2="","",VLOOKUP(C2,[1]ISO辞書!A:C,3,FALSE)) -> Slovenia | C2: スロベニア | D2: スロベニア総選挙 | E2: スロベニアの総選挙が行われるも、与野党いずれも単独過半数を獲得できず、小党が連立の鍵を握る情勢となった | M2: =IF(J2="","",VLOOKUP(J2,[1]ISO辞書!A:B,2,FALSE)) | N2: =IF(K2="","",VLOOKUP(K2,[1]ISO辞書!A:B,2,FALSE)) | O2: =IF(L2="","",VLOOKUP(L2,[1]ISO辞書!A:B,2,FALSE)) | P2: =_xlfn.TEXTJOIN(";",TRUE,M2:O2) | Q2: 政局の不安定化は政策決定の遅れや対外姿勢の変化を招き、欧州での投資環境と対日関係にも影響を及ぼす可能性がある。 | R2: 国内政治 | S2: 46103 | T2: Reuters | U2: https://www.reuters.com/world/europe/slovenians-vote-tight-race-between-liberals-populist-right-2026-03-22/ | V2: 2
A3: =IF(C3="","",VLOOKUP(C3,[1]ISO辞書!A:C,2,FALSE)) -> TCD | B3: =IF(C3="","",VLOOKUP(C3,[1]ISO辞書!A:C,3,FALSE)) -> Chad | C3: チャド | D3: チャドがスーダン難民をめぐり国境へ軍を展開 | E3: チャドはスーダンからの越境ドローン攻撃を受け反撃準備を命じ、かつ国境地帯の難民約2,300人を内陸に緊急移転させ、国境における警戒を強めた | J3: スーダン | M3: =IF(J3="","",VLOOKUP(J3,[1]ISO辞書!A:B,2,FALSE)) -> SDN | N3: =IF(K3="","",VLOOKUP(K3,[1]ISO辞書!A:B,2,FALSE)) | O3: =IF(L3="","",VLOOKUP(L3,[1]ISO辞書!A:B,2,FALSE)) | P3: =_xlfn.TEXTJOIN(";",TRUE,M3:O3) -> SDN | Q3: 国境での戦闘と難民移動は域内の不安定化と人道支援需要を強め、日本の人道支援や国際的な安全保障協力にも影響を与える可能性がある。 | R3: 軍事 | S3: 46104 | T3: Reuters | U3: https://www.reuters.com/world/africa/chad-relocates-sudan-refugees-army-deploys-near-border-2026-03-23/ | V3: 1
A4: =IF(C4="","",VLOOKUP(C4,[1]ISO辞書!A:C,2,FALSE)) -> CRI | B4: =IF(C4="","",VLOOKUP(C4,[1]ISO辞書!A:C,3,FALSE)) -> Costa Rica | C4: コスタリカ | D4: コスタリカ、アメリカからの移民送還者受け入れへ | E4: アメリカとコスタリカは、米国が他国から送還する移民をコスタリカが受け入れる合意に署名した。週最大25人がコスタリカに移送され、米国が資金支援を行う。 | J4: アメリカ | M4: =IF(J4="","",VLOOKUP(J4,[1]ISO辞書!A:B,2,FALSE)) -> USA | N4: =IF(K4="","",VLOOKUP(K4,[1]ISO辞書!A:B,2,FALSE)) | O4: =IF(L4="","",VLOOKUP(L4,[1]ISO辞書!A:B,2,FALSE)) | P4: =_xlfn.TEXTJOIN(";",TRUE,M4:O4) -> USA | Q4: 中米の移民負担を分散し、米国の移民政策の運用負担の軽減が見込まれる。日本への直接影響は限定的だが、国際移民管理と多国間支援の在り方に示唆を与える。 | R4: 外交 | S4: 46104 | T4: Reuters | U4: https://www.reuters.com/world/americas/costa-rica-plans-accept-us-sent-migrants-other-countries-2026-03-24/ | V4: 4
A5: =IF(C5="","",VLOOKUP(C5,[1]ISO辞書!A:C,2,FALSE)) -> CHN | B5: =IF(C5="","",VLOOKUP(C5,[1]ISO辞書!A:C,3,FALSE)) -> China | C5: 中国 | D5: 香港警察、外国人へのパスワード取得権拡大 | E5: 香港政府が新法を制定し、警察にスマートフォンやコンピューターのパスワード提出を求める権限を付与した。これにより捜査当局は国家安全や重大犯罪の捜査でデジタル証拠へのアクセスを強化する。 | M5: =IF(J5="","",VLOOKUP(J5,[1]ISO辞書!A:B,2,FALSE)) | N5: =IF(K5="","",VLOOKUP(K5,[1]ISO辞書!A:B,2,FALSE)) | O5: =IF(L5="","",VLOOKUP(L5,[1]ISO辞書!A:B,2,FALSE)) | P5: =_xlfn.TEXTJOIN(";",TRUE,M5:O5) | Q5: 市民のプライバシー懸念が強まり、人権問題や対中投資判断、同国への渡航に影響を与える可能性がある。 | R5: 国内政治 | S5: 46104 | T5: Reuters | U5: https://www.reuters.com/world/china/hong-kong-police-given-new-powers-obtain-phone-computer-passwords-2026-03-23/ | V5: 5
A6: =IF(C6="","",VLOOKUP(C6,[1]ISO辞書!A:C,2,FALSE)) -> ISR | B6: =IF(C6="","",VLOOKUP(C6,[1]ISO辞書!A:C,3,FALSE)) -> Israel | C6: イスラエル | D6: イスラエル閣僚がレバノン南部を併合宣言 | E6: イスラエルの極右政党の大臣が南レバノンの併合を公に主張し、国土防衛と反テロをその理由に挙げた。声明は地域の軍事的緊張と国際的な非難を招いている。 | J6: レバノン | M6: =IF(J6="","",VLOOKUP(J6,[1]ISO辞書!A:B,2,FALSE)) -> LBN | N6: =IF(K6="","",VLOOKUP(K6,[1]ISO辞書!A:B,2,FALSE)) | O6: =IF(L6="","",VLOOKUP(L6,[1]ISO辞書!A:B,2,FALSE)) | P6: =_xlfn.TEXTJOIN(";",TRUE,M6:O6) -> LBN | Q6: 中東地域での緊張が高まり、海上輸送やエネルギー価格への波及が懸念。日本の外交・経済にも負担を及ぼす恐れがある。 | R6: 紛争 | S6: 46104 | T6: Reuters | U6: https://www.reuters.com/world/middle-east/israeli-minister-calls-annexation-southern-lebanon-2026-03-23/ | V6: 4
A7: =IF(C7="","",VLOOKUP(C7,[1]ISO辞書!A:C,2,FALSE)) -> ITA | B7: =IF(C7="","",VLOOKUP(C7,[1]ISO辞書!A:C,3,FALSE)) -> Italy | C7: イタリア | D7: イタリアの司法改革案が国民投票にて否決 | E7: 国民投票で与党が推進した司法改革案が否決され、メローニ首相の政治的影響力に打撃となった。投票率は約60%で反対が約54%を占めた。 | M7: =IF(J7="","",VLOOKUP(J7,[1]ISO辞書!A:B,2,FALSE)) | N7: =IF(K7="","",VLOOKUP(K7,[1]ISO辞書!A:B,2,FALSE)) | O7: =IF(L7="","",VLOOKUP(L7,[1]ISO辞書!A:B,2,FALSE)) | P7: =_xlfn.TEXTJOIN(";",TRUE,M7:O7) | Q7: メローニ政権の求心力低下が国内政局を不安定化させ、欧州での政策連携や対日関係にも影響を及ぼす可能性がある。 | R7: 国内政治 | S7: 46104 | T7: Reuters | U7: https://www.reuters.com/world/europe/exit-polls-suggest-italys-meloni-has-narrowly-lost-justice-referendum-vote-2026-03-23/ | V7: 5
A8: =IF(C8="","",VLOOKUP(C8,[1]ISO辞書!A:C,2,FALSE)) -> JPN | B8: =IF(C8="","",VLOOKUP(C8,[1]ISO辞書!A:C,3,FALSE)) -> Japan | C8: 日本 | D8: 日本、対中関係を「最重要」から格下げ | E8: 日本政府は2026年外交青書案にて、中国との関係を「最重要」との文言を外す方針を示し、対中政策を修正すると発表した。 | J8: 中国 | M8: =IF(J8="","",VLOOKUP(J8,[1]ISO辞書!A:B,2,FALSE)) -> CHN | N8: =IF(K8="","",VLOOKUP(K8,[1]ISO辞書!A:B,2,FALSE)) | O8: =IF(L8="","",VLOOKUP(L8,[1]ISO辞書!A:B,2,FALSE)) | P8: =_xlfn.TEXTJOIN(";",TRUE,M8:O8) -> CHN | Q8: 文言変更は日中関係の見直しを意味し、経済安全保障の観点から中国で活動する日経企業にも影響が生じうる。 | R8: 外交 | S8: 46105 | T8: Reuters | U8: https://www.reuters.com/world/china/japan-drop-most-important-tag-china-ties-2026-03-24/ | V8: 5
A9: =IF(C9="","",VLOOKUP(C9,[1]ISO辞書!A:C,2,FALSE)) -> ISR | B9: =IF(C9="","",VLOOKUP(C9,[1]ISO辞書!A:C,3,FALSE)) -> Israel | C9: イスラエル | D9: イスラエルがレバノン南部へ緩衝地帯設置計画を発表 | E9: イスラエルが南レバノンの一部を「緩衝地帯」として分離する計画を進め、同地域のインフラや市民に被害が発生している。 | J9: レバノン | M9: =IF(J9="","",VLOOKUP(J9,[1]ISO辞書!A:B,2,FALSE)) -> LBN | N9: =IF(K9="","",VLOOKUP(K9,[1]ISO辞書!A:B,2,FALSE)) | O9: =IF(L9="","",VLOOKUP(L9,[1]ISO辞書!A:B,2,FALSE)) | P9: =_xlfn.TEXTJOIN(";",TRUE,M9:O9) -> LBN | Q9: イスラエル軍による攻撃は中東地域における対立の構図を強め、地域の不安定化から中東からのエネルギー供給に影響の出る可能性がある。 | R9: 紛争 | S9: 46105 | T9: Reuters | U9: https://www.reuters.com/graphics/IRAN-CRISIS/LEBANON-ISRAEL-INFRASTRUCTURE/gkvlklaxypb/ | V9: 5
A10: =IF(C10="","",VLOOKUP(C10,[1]ISO辞書!A:C,2,FALSE)) -> EU | B10: =IF(C10="","",VLOOKUP(C10,[1]ISO辞書!A:C,3,FALSE)) -> EU | C10: 欧州連合 | D10: 欧州連合・オーストラリアが貿易協定を締結 | E10: EUとオーストラリアが包括的通商協定で合意し、関税の削減やサービス分野の市場開放、投資保護などの主要条項が発表された。 | J10: オーストラリア | M10: =IF(J10="","",VLOOKUP(J10,[1]ISO辞書!A:B,2,FALSE)) -> AUS | N10: =IF(K10="","",VLOOKUP(K10,[1]ISO辞書!A:B,2,FALSE)) | O10: =IF(L10="","",VLOOKUP(L10,[1]ISO辞書!A:B,2,FALSE)) | P10: =_xlfn.TEXTJOIN(";",TRUE,M10:O10) -> AUS | Q10: 新協定によりEUとオーストラリア間の貿易が活性化され、日本企業の国際競争にも影響を与え得る。 | R10: 貿易 | S10: 46105 | T10: Reuters | U10: https://www.reuters.com/business/highlights-eu-australia-trade-agreement-2026-03-24/ | V10: 5
A11: =IF(C11="","",VLOOKUP(C11,[1]ISO辞書!A:C,2,FALSE)) -> MEX | B11: =IF(C11="","",VLOOKUP(C11,[1]ISO辞書!A:C,3,FALSE)) -> Mexico | C11: メキシコ | D11: メキシコがキューバ医師協定維持を表明 | E11: メキシコ政府は、医療人材不足を補うためのキューバとの意思協定を維持すると表明し、同国の医療を支える姿勢を示した。 | J11: キューバ | M11: =IF(J11="","",VLOOKUP(J11,[1]ISO辞書!A:B,2,FALSE)) -> CUB | N11: =IF(K11="","",VLOOKUP(K11,[1]ISO辞書!A:B,2,FALSE)) | O11: =IF(L11="","",VLOOKUP(L11,[1]ISO辞書!A:B,2,FALSE)) | P11: =_xlfn.TEXTJOIN(";",TRUE,M11:O11) -> CUB | R11: 外交 | S11: 46106 | T11: Reuters | U11: https://www.reuters.com/world/americas/mexico-uphold-cuban-doctor-agreement-president-says-2026-03-25/ | V11: 2
A12: =IF(C12="","",VLOOKUP(C12,[1]ISO辞書!A:C,2,FALSE)) -> CYP | B12: =IF(C12="","",VLOOKUP(C12,[1]ISO辞書!A:C,3,FALSE)) -> Cyprus | C12: キプロス | D12: キプロス、イギリスと基地協議 | E12: キプロスが同国内にあるイギリス軍の基地について、イギリスと協議を開始したと発表。基地の運用や権限を巡る対話が開始される。 | J12: イギリス | M12: =IF(J12="","",VLOOKUP(J12,[1]ISO辞書!A:B,2,FALSE)) -> GBR | N12: =IF(K12="","",VLOOKUP(K12,[1]ISO辞書!A:B,2,FALSE)) | O12: =IF(L12="","",VLOOKUP(L12,[1]ISO辞書!A:B,2,FALSE)) | P12: =_xlfn.TEXTJOIN(";",TRUE,M12:O12) -> GBR | Q12: 地中海での安全保障協定が進めば、地中海における輸送航路の安定化が期待される。 | R12: 安全保障 | S12: 46106 | T12: Reuters | U12: https://www.reuters.com/world/uk/cyprus-has-opened-discussion-with-uk-over-its-bases-president-says-2026-03-25/ | V12: 4
A13: =IF(C13="","",VLOOKUP(C13,[1]ISO辞書!A:C,2,FALSE)) -> DNK | B13: =IF(C13="","",VLOOKUP(C13,[1]ISO辞書!A:C,3,FALSE)) -> Denmark | C13: デンマーク | D13: デンマーク首相が辞任表明 | E13: デンマークのフリデリクセン首相は選挙での敗北を受け辞任を表明。政権移行の手続きと新政権樹立の準備が始まる | M13: =IF(J13="","",VLOOKUP(J13,[1]ISO辞書!A:B,2,FALSE)) | N13: =IF(K13="","",VLOOKUP(K13,[1]ISO辞書!A:B,2,FALSE)) | O13: =IF(L13="","",VLOOKUP(L13,[1]ISO辞書!A:B,2,FALSE)) | P13: =_xlfn.TEXTJOIN(";",TRUE,M13:O13) | Q13: 政権交代はデンマークの国内外の政策見直しを招き、北欧諸国との協調やEU政策に影響を与える可能性がある。 | R13: 国内政治 | S13: 46106 | T13: Reuters | U13: https://www.reuters.com/world/europe/denmarks-prime-minister-hands-government-resignation-after-election-defeat-2026-03-25/ | V13: 3
A14: =IF(C14="","",VLOOKUP(C14,[1]ISO辞書!A:C,2,FALSE)) -> GBR | B14: =IF(C14="","",VLOOKUP(C14,[1]ISO辞書!A:C,3,FALSE)) -> Britain | C14: イギリス | D14: イギリスとトルコが防空協定に署名 | E14: イギリスとトルコが戦闘機20機の導入に向けた訓練・支援契約に署名、総額80億ポンドの合意を前進させた。 | J14: トルコ | M14: =IF(J14="","",VLOOKUP(J14,[1]ISO辞書!A:B,2,FALSE)) -> TUR | N14: =IF(K14="","",VLOOKUP(K14,[1]ISO辞書!A:B,2,FALSE)) | O14: =IF(L14="","",VLOOKUP(L14,[1]ISO辞書!A:B,2,FALSE)) | P14: =_xlfn.TEXTJOIN(";",TRUE,M14:O14) -> TUR | Q14: NATO東側の防空強化につながり、欧州の防衛産業と安全保障協力の流れを後押しする。日本の装備調達議論にも参考になりうる。 | R14: 安全保障 | S14: 46106 | T14: Reuters | U14: https://www.reuters.com/business/aerospace-defense/uk-turkey-sign-multi-billion-pound-air-defence-deal-2026-03-25/ | V14: 4
A15: =IF(C15="","",VLOOKUP(C15,[1]ISO辞書!A:C,2,FALSE)) -> KEN | B15: =IF(C15="","",VLOOKUP(C15,[1]ISO辞書!A:C,3,FALSE)) -> Kenya | C15: ケニア | D15: ケニアが中国との貿易協定に最終合意 | E15: ケニアのルト大統領は、中国との貿易交渉がまとまり、ケニアの輸出品の98％に関税ゼロを認める最終的な合意が取られたと発表した | J15: 中国 | M15: =IF(J15="","",VLOOKUP(J15,[1]ISO辞書!A:B,2,FALSE)) -> CHN | N15: =IF(K15="","",VLOOKUP(K15,[1]ISO辞書!A:B,2,FALSE)) | O15: =IF(L15="","",VLOOKUP(L15,[1]ISO辞書!A:B,2,FALSE)) | P15: =_xlfn.TEXTJOIN(";",TRUE,M15:O15) -> CHN | Q15: 中国のアフリカ進出が一段と進み、資源や市場をめぐる競争が強まる。日本企業のアフリカ展開にも影響しうる。 | R15: 貿易 | S15: 46106 | T15: Reuters | U15: https://www.reuters.com/world/africa/kenya-finalises-trade-deal-with-china-president-says-2026-03-25/ | V15: 3
A16: =IF(C16="","",VLOOKUP(C16,[1]ISO辞書!A:C,2,FALSE)) -> USA | B16: =IF(C16="","",VLOOKUP(C16,[1]ISO辞書!A:C,3,FALSE)) -> America | C16: アメリカ | D16: トランプ氏、マドゥロ大統領への追加訴追を示唆 | E16: トランプ大統領は、拘束中のベネズエラのマドゥロ氏について、追加の訴追を進めると表明した。 | J16: ベネズエラ | M16: =IF(J16="","",VLOOKUP(J16,[1]ISO辞書!A:B,2,FALSE)) -> VEN | N16: =IF(K16="","",VLOOKUP(K16,[1]ISO辞書!A:B,2,FALSE)) | O16: =IF(L16="","",VLOOKUP(L16,[1]ISO辞書!A:B,2,FALSE)) | P16: =_xlfn.TEXTJOIN(";",TRUE,M16:O16) -> VEN | Q16: アメリカの対ベネズエラ圧力が強まれば、移民問題や原油市場の不安定化が続き、日本にも間接的な影響が及ぶ。 | R16: 外交 | S16: 46107 | T16: Reuters | U16: https://www.reuters.com/world/americas/trump-says-venezuelas-maduro-face-additional-charges-2026-03-26/ | V16: 3
A17: =IF(C17="","",VLOOKUP(C17,[1]ISO辞書!A:C,2,FALSE)) -> PAK | B17: =IF(C17="","",VLOOKUP(C17,[1]ISO辞書!A:C,3,FALSE)) -> Pakistan | C17: パキスタン | D17: パキスタン、アフガニスタンで軍事作戦継続 | E17: パキスタン外務省は、アフガニスタンへの軍事行動を再開したと発表し、停戦への期待が後退した。 | J17: アフガニスタン | M17: =IF(J17="","",VLOOKUP(J17,[1]ISO辞書!A:B,2,FALSE)) -> AFG | N17: =IF(K17="","",VLOOKUP(K17,[1]ISO辞書!A:B,2,FALSE)) | O17: =IF(L17="","",VLOOKUP(L17,[1]ISO辞書!A:B,2,FALSE)) | P17: =_xlfn.TEXTJOIN(";",TRUE,M17:O17) -> AFG | Q17: イラン情勢を含めた中東から南アジア地域での緊張拡大が危惧される。物流に影響が出るほか、日本企業の中東やアジアにおける事業にもリスク要因となる。 | R17: 紛争 | S17: 46107 | T17: Reuters | U17: https://www.reuters.com/world/asia-pacific/pakistan-continuing-military-operations-against-afghanistan-pakistan-foreign-2026-03-26/ | V17: 5
A18: =IF(C18="","",VLOOKUP(C18,[1]ISO辞書!A:C,2,FALSE)) -> USA | B18: =IF(C18="","",VLOOKUP(C18,[1]ISO辞書!A:C,3,FALSE)) -> America | C18: アメリカ | D18: トランプ大統領、イランのエネルギー施設への攻撃を一時停止 | E18: トランプ大統領は、イランの要請を受けてエネルギー施設への攻撃を10日間止めるとし、停戦交渉は順調だと述べた。イラン側はアメリカ側の停戦案を不公平だと批判した。 | J18: イラン | M18: =IF(J18="","",VLOOKUP(J18,[1]ISO辞書!A:B,2,FALSE)) -> IRN | N18: =IF(K18="","",VLOOKUP(K18,[1]ISO辞書!A:B,2,FALSE)) | O18: =IF(L18="","",VLOOKUP(L18,[1]ISO辞書!A:B,2,FALSE)) | P18: =_xlfn.TEXTJOIN(";",TRUE,M18:O18) -> IRN | Q18: 中東の緊張が和らげば原油高の圧力は弱まるが、交渉が崩れれば日本のエネルギー輸入コスト高が危惧される。 | R18: 紛争 | S18: 46107 | T18: Reuters | U18: https://www.reuters.com/world/asia-pacific/iran-says-it-is-reviewing-us-ceasefire-plan-no-talks-trump-says-tehran-leaders-2026-03-26/ | V18: 5
A19: =IF(C19="","",VLOOKUP(C19,[1]ISO辞書!A:C,2,FALSE)) -> IRN | B19: =IF(C19="","",VLOOKUP(C19,[1]ISO辞書!A:C,3,FALSE)) -> Iran | C19: イラン | D19: アメリカがアラクチ外相らを攻撃対象から一時解除 | E19: パキスタンの要請により、イランのアラグチ外相とカリバフ議長がアメリカとイスラエルの攻撃対象から外された。 | J19: アメリカ | K19: パキスタン | M19: =IF(J19="","",VLOOKUP(J19,[1]ISO辞書!A:B,2,FALSE)) -> USA | N19: =IF(K19="","",VLOOKUP(K19,[1]ISO辞書!A:B,2,FALSE)) -> PAK | O19: =IF(L19="","",VLOOKUP(L19,[1]ISO辞書!A:B,2,FALSE)) | P19: =_xlfn.TEXTJOIN(";",TRUE,M19:O19) -> USA;PAK | Q19: パキスタンの仲介による対話継続により停戦成立が期待されるが状況は不透明。 | R19: 紛争 | S19: 46107 | T19: Reuters | U19: https://www.reuters.com/world/asia-pacific/israel-took-irans-araqchi-qalibaf-off-hit-list-pakistan-request-pakistani-2026-03-26/ | V19: 5
A20: =IF(C20="","",VLOOKUP(C20,[1]ISO辞書!A:C,2,FALSE)) -> UKR | B20: =IF(C20="","",VLOOKUP(C20,[1]ISO辞書!A:C,3,FALSE)) -> Ukraine | C20: ウクライナ | D20: ウクライナ、ロシアのエネルギー施設へ圧力 | E20: ゼレンスキー大統領は、国際的なロシアへの石油制裁が緩んだ後も、長距離攻撃で石油施設を狙い圧力をかけ続ける方針だと述べた。 | J20: ロシア | M20: =IF(J20="","",VLOOKUP(J20,[1]ISO辞書!A:B,2,FALSE)) -> RUS | N20: =IF(K20="","",VLOOKUP(K20,[1]ISO辞書!A:B,2,FALSE)) | O20: =IF(L20="","",VLOOKUP(L20,[1]ISO辞書!A:B,2,FALSE)) | P20: =_xlfn.TEXTJOIN(";",TRUE,M20:O20) -> RUS | Q20: ロシア産原油の輸出混乱はエネルギー価格を押し上げやすく、資源輸入国の日本にはコスト上昇圧力となる。 | R20: 紛争 | S20: 46107 | T20: Reuters | U20: https://www.reuters.com/business/energy/ukraine-using-strikes-pressure-russia-after-oil-sanctions-eased-zelenskiy-says-2026-03-26/ | V20: 5
A21: =IF(C21="","",VLOOKUP(C21,[1]ISO辞書!A:C,2,FALSE)) -> USA | B21: =IF(C21="","",VLOOKUP(C21,[1]ISO辞書!A:C,3,FALSE)) -> America | C21: アメリカ | D21: トランプ大統領、次はキューバ言及 | E21: トランプ大統領が演説で軍事成果を強調し、次の標的としてキューバに言及。緊張拡大の懸念が浮上。 | J21: キューバ | M21: =IF(J21="","",VLOOKUP(J21,[1]ISO辞書!A:B,2,FALSE)) -> CUB | N21: =IF(K21="","",VLOOKUP(K21,[1]ISO辞書!A:B,2,FALSE)) | O21: =IF(L21="","",VLOOKUP(L21,[1]ISO辞書!A:B,2,FALSE)) | P21: =_xlfn.TEXTJOIN(";",TRUE,M21:O21) -> CUB | Q21: 対キューバ圧力が強まれば中南米の緊張が増し、資源市場や日系企業の南米事業にも波及しうる。 | R21: 軍事 | S21: 46108 | T21: Reuters | U21: https://www.reuters.com/world/americas/trump-says-cuba-is-next-speech-touting-us-military-successes-2026-03-27/ | V21: 4
A22: =IF(C22="","",VLOOKUP(C22,[1]ISO辞書!A:C,2,FALSE)) -> CAN | B22: =IF(C22="","",VLOOKUP(C22,[1]ISO辞書!A:C,3,FALSE)) -> Canada | C22: カナダ | D22: カナダ、メルコスール協定狙う | E22: カナダがメルコスールとの自由貿易協定締結に向けた交渉加速を表明。2026年9～10月の署名と年内の合意が目標であると発表される。 | J22: ブラジル | K22: アルゼンチン | L22: パラグアイ | M22: =IF(J22="","",VLOOKUP(J22,[1]ISO辞書!A:B,2,FALSE)) -> BRA | N22: =IF(K22="","",VLOOKUP(K22,[1]ISO辞書!A:B,2,FALSE)) -> ARG | O22: =IF(L22="","",VLOOKUP(L22,[1]ISO辞書!A:B,2,FALSE)) -> PRY | P22: =_xlfn.TEXTJOIN(";",TRUE,M22:O22) -> BRA;ARG;PRY | Q22: アメリカとカナダの関係悪化により、北米と南米における新たな貿易協定の締結の可能性。サプライチェーン再編が進み日本企業の進出戦略やサプライチェーンにも影響。 | R22: 貿易 | S22: 46108 | T22: Reuters | U22: https://www.reuters.com/world/canada-eyes-mercosur-pact-by-autumn-2026-03-27/ | V22: 4
A23: =IF(C23="","",VLOOKUP(C23,[1]ISO辞書!A:C,2,FALSE)) -> EU | B23: =IF(C23="","",VLOOKUP(C23,[1]ISO辞書!A:C,3,FALSE)) -> EU | C23: 欧州連合 | D23: EＵとTPPがデジタル分野の合意を形成 | E23: EUとCPTPP参加国は、越境ECやデータ流通を含むデジタル貿易協定の協議を進めることで一致。カナダの貿易相は歴史的合意になりうると述べた。 | J23: CPTPP | M23: =IF(J23="","",VLOOKUP(J23,[1]ISO辞書!A:B,2,FALSE)) -> CPTPP | N23: =IF(K23="","",VLOOKUP(K23,[1]ISO辞書!A:B,2,FALSE)) | O23: =IF(L23="","",VLOOKUP(L23,[1]ISO辞書!A:B,2,FALSE)) | P23: =_xlfn.TEXTJOIN(";",TRUE,M23:O23) -> CPTPP | Q23: 日本を含むCPTPP域内でデジタル取引の標準化が進めば、越境ECやデータ連携がしやすくなり、日本企業にも追い風となる。 | R23: 貿易 | S23: 46108 | T23: Reuters | U23: https://www.reuters.com/world/americas/eu-cptpp-agree-progress-with-historic-digital-trade-deal-canadas-international-2026-03-27/ | V23: 5
A24: =IF(C24="","",VLOOKUP(C24,[1]ISO辞書!A:C,2,FALSE)) -> NPL | B24: =IF(C24="","",VLOOKUP(C24,[1]ISO辞書!A:C,3,FALSE)) -> Nepal | C24: ネパール | D24: ネパール首相にシャー氏が就任 | E24: シャハ氏がネパール首相に就任。雇用創出と政治的安定の回復が期待される。若者世代の抗議活動による政治的変動から、再建を進める局面に入った。 | M24: =IF(J24="","",VLOOKUP(J24,[1]ISO辞書!A:B,2,FALSE)) | N24: =IF(K24="","",VLOOKUP(K24,[1]ISO辞書!A:B,2,FALSE)) | O24: =IF(L24="","",VLOOKUP(L24,[1]ISO辞書!A:B,2,FALSE)) | P24: =_xlfn.TEXTJOIN(";",TRUE,M24:O24) | Q24: ネパールの政局が安定すれば南アジアの不確実性は和らぐが、混乱が続けば周辺国との経済関係にも響く可能性。 | R24: その他 | S24: 46108 | T24: Reuters | U24: https://www.reuters.com/world/china/ex-rapper-shah-sworn-nepal-prime-minister-after-sweeping-election-win-2026-03-27/ | V24: 2
A25: =IF(C25="","",VLOOKUP(C25,[1]ISO辞書!A:C,2,FALSE)) -> PRK | B25: =IF(C25="","",VLOOKUP(C25,[1]ISO辞書!A:C,3,FALSE)) -> North Korea | C25: 北朝鮮 | D25: 北朝鮮とベラルーシが友好条約に署名 | E25: 金正恩総書記とルカシェンコ大統領が平壌で会談し、友好条約と外交・農業・教育・公衆衛生などの協力文書に署名。両国関係が格上げされた。 | J25: ベラルーシ | M25: =IF(J25="","",VLOOKUP(J25,[1]ISO辞書!A:B,2,FALSE)) -> BLR | N25: =IF(K25="","",VLOOKUP(K25,[1]ISO辞書!A:B,2,FALSE)) | O25: =IF(L25="","",VLOOKUP(L25,[1]ISO辞書!A:B,2,FALSE)) | P25: =_xlfn.TEXTJOIN(";",TRUE,M25:O25) -> BLR | Q25: 北朝鮮の対外連携が広がれば制裁による包囲網の効果が弱まり、東アジアの安全保障に不安が残る。 | R25: 外交 | S25: 46108 | T25: Reuters | U25: https://www.reuters.com/world/asia-pacific/north-korea-belarus-sign-friendship-treaty-kcna-says-2026-03-26/ | V25: 5
A26: =IF(C26="","",VLOOKUP(C26,[1]ISO辞書!A:C,2,FALSE)) -> UKR | B26: =IF(C26="","",VLOOKUP(C26,[1]ISO辞書!A:C,3,FALSE)) -> Ukraine | C26: ウクライナ | D26: ウクライナとサウジアラビアが防衛協力に合意 | E26: ウクライナとサウジアラビアが防衛協力協定を結び、将来の契約や技術協力、投資の土台になるとゼレンスキー大統領が表明。アメリカの支援不透明感が強まる中、湾岸地域での支持を広げる狙いがある。 | J26: サウジアラビア | M26: =IF(J26="","",VLOOKUP(J26,[1]ISO辞書!A:B,2,FALSE)) -> SAU | N26: =IF(K26="","",VLOOKUP(K26,[1]ISO辞書!A:B,2,FALSE)) | O26: =IF(L26="","",VLOOKUP(L26,[1]ISO辞書!A:B,2,FALSE)) | P26: =_xlfn.TEXTJOIN(";",TRUE,M26:O26) -> SAU | Q26: 支援の軸が欧米以外にも広がれば、ロシアとの戦争の長期化への備えと、中東における外交の再編が進む。日本にも原油や安全保障面での影響が及ぶ可能性あり。 | R26: 安全保障 | S26: 46108 | T26: Reuters | U26: https://www.reuters.com/business/aerospace-defense/ukraine-saudi-arabia-sign-deal-defence-cooperation-zelenskiy-says-2026-03-27/ | V26: 5
A27: =IF(C27="","",VLOOKUP(C27,[1]ISO辞書!A:C,2,FALSE)) -> COD | B27: =IF(C27="","",VLOOKUP(C27,[1]ISO辞書!A:C,3,FALSE)) -> Democratic Republic of the Congo | C27: コンゴ民主共和国 | D27: DRコンゴが中国との鉱業協力強化 | E27: コンゴ民主共和国は中国と鉱山分野の協力を深める合意を締結。コバルトの最大産地をめぐり、米中が影響力を競う構図が強まっている。 | J27: 中国 | M27: =IF(J27="","",VLOOKUP(J27,[1]ISO辞書!A:B,2,FALSE)) -> CHN | N27: =IF(K27="","",VLOOKUP(K27,[1]ISO辞書!A:B,2,FALSE)) | O27: =IF(L27="","",VLOOKUP(L27,[1]ISO辞書!A:B,2,FALSE)) | P27: =_xlfn.TEXTJOIN(";",TRUE,M27:O27) -> CHN | Q27: リチウムイオン電池の原料の供給網に直結するため、日本のEVや蓄電池産業の調達先分散にも関係しうる。 | R27: 貿易 | S27: 46108 | T27: Reuters | U27: https://www.reuters.com/world/africa/congo-china-deepen-mining-ties-us-pushes-rival-minerals-pact-2026-03-27/ | V27: 4
A28: =IF(C28="","",VLOOKUP(C28,[1]ISO辞書!A:C,2,FALSE)) -> CHN | B28: =IF(C28="","",VLOOKUP(C28,[1]ISO辞書!A:C,3,FALSE)) -> China | C28: 中国 | D28: 比中、南シナ海協議再開へ | E28: フィリピンと中国が南シナ海をめぐる高官協議を約1年ぶりに再開。石油や天然ガス調達における協力や、エネルギー・肥料の供給安定を協議した。比マルコス大統領が国家エネルギー非常事態を宣言した直後の対話。 | J28: フィリピン | M28: =IF(J28="","",VLOOKUP(J28,[1]ISO辞書!A:B,2,FALSE)) -> PHL | N28: =IF(K28="","",VLOOKUP(K28,[1]ISO辞書!A:B,2,FALSE)) | O28: =IF(L28="","",VLOOKUP(L28,[1]ISO辞書!A:B,2,FALSE)) | P28: =_xlfn.TEXTJOIN(";",TRUE,M28:O28) -> PHL | Q28: 海上摩擦の緩和は海運とエネルギー市場の安定に寄与し、日本の燃料調達リスクの抑制にもつながる。 | R28: 安全保障 | S28: 46109 | T28: Reuters | U28: https://www.reuters.com/business/energy/manila-beijing-resume-talks-south-china-sea-energy-security-2026-03-28/ | V28: 4
A29: =IF(C29="","",VLOOKUP(C29,[1]ISO辞書!A:C,2,FALSE)) -> IDN | B29: =IF(C29="","",VLOOKUP(C29,[1]ISO辞書!A:C,3,FALSE)) -> Indonesia | C29: インドネシア | D29: インドネシア、未成年SNS規制が施行 | E29: インドネシアが16歳未満のSNS利用を制限する新ルールを開始。運用方法にはなお不透明さが残る。 | M29: =IF(J29="","",VLOOKUP(J29,[1]ISO辞書!A:B,2,FALSE)) | N29: =IF(K29="","",VLOOKUP(K29,[1]ISO辞書!A:B,2,FALSE)) | O29: =IF(L29="","",VLOOKUP(L29,[1]ISO辞書!A:B,2,FALSE)) | P29: =_xlfn.TEXTJOIN(";",TRUE,M29:O29) | Q29: 未成年への保護強化は、アジアのSNS事業者に年齢確認と監視強化を迫り、日本の規制議論にも影響が起きうる。 | R29: その他 | S29: 46109 | T29: Reuters | U29: https://www.reuters.com/business/media-telecom/indonesias-social-media-curbs-kids-set-saturday-few-know-how-it-will-work-2026-03-27/ | V29: 3
A30: =IF(C30="","",VLOOKUP(C30,[1]ISO辞書!A:C,2,FALSE)) -> UKR | B30: =IF(C30="","",VLOOKUP(C30,[1]ISO辞書!A:C,3,FALSE)) -> Ukraine | C30: ウクライナ | D30: ウクライナがUAE・カタールと防衛協力 | E30: ウクライナがUAEと防衛分野で協力に合意。カタールともミサイルや無人機対策を含む協定を結んだ。ゼレンスキー大統領は湾岸歴訪で支援の幅を広げようとしている。 | J30: UAE | K30: カタール | M30: =IF(J30="","",VLOOKUP(J30,[1]ISO辞書!A:B,2,FALSE)) -> ARE | N30: =IF(K30="","",VLOOKUP(K30,[1]ISO辞書!A:B,2,FALSE)) -> QAT | O30: =IF(L30="","",VLOOKUP(L30,[1]ISO辞書!A:B,2,FALSE)) | P30: =_xlfn.TEXTJOIN(";",TRUE,M30:O30) -> ARE;QAT | Q30: ウクライナと湾岸諸国との結びつきが強まることで欧米中心の同国への支援が多角化が期待。中東を含む国際秩序の変化は日本の経済外交にも関係が及びうる。 | R30: 安全保障 | S30: 46109 | T30: Reuters | U30: https://www.reuters.com/world/middle-east/ukraine-uae-agree-cooperate-defence-zelenskiy-says-2026-03-28/ | V30: 5
A31: =IF(C31="","",VLOOKUP(C31,[1]ISO辞書!A:C,2,FALSE)) -> NPL | B31: =IF(C31="","",VLOOKUP(C31,[1]ISO辞書!A:C,3,FALSE)) -> Nepal | C31: ネパール | D31: ネパールの前首相が逮捕される | E31: ネパール警察が前首相のオリ氏を逮捕。2025年9月の反汚職デモで多数の死者が出た対応を巡っての逮捕となる。 | M31: =IF(J31="","",VLOOKUP(J31,[1]ISO辞書!A:B,2,FALSE)) | N31: =IF(K31="","",VLOOKUP(K31,[1]ISO辞書!A:B,2,FALSE)) | O31: =IF(L31="","",VLOOKUP(L31,[1]ISO辞書!A:B,2,FALSE)) | P31: =_xlfn.TEXTJOIN(";",TRUE,M31:O31) | R31: 国内政治 | S31: 46109 | T31: Reuters | U31: https://www.reuters.com/world/asia-pacific/nepals-ex-pm-oli-held-over-deaths-during-gen-z-protests-2026-03-28/ | V31: 2
A32: =IF(C32="","",VLOOKUP(C32,[1]ISO辞書!A:C,2,FALSE)) -> YEM | B32: =IF(C32="","",VLOOKUP(C32,[1]ISO辞書!A:C,3,FALSE)) -> Yemen | C32: イエメン | D32: フーシ派がイランの戦線へ参加表明 | E32: パキスタンがイラン紛争の終結に向けた協議準備を進める一方、フーシ派がイスラエルへの攻撃に加わり、紅海周辺の海上輸送リスクが高まった。 | J32: イラン | K32: アメリカ | L32: イスラエル | M32: =IF(J32="","",VLOOKUP(J32,[1]ISO辞書!A:B,2,FALSE)) -> IRN | N32: =IF(K32="","",VLOOKUP(K32,[1]ISO辞書!A:B,2,FALSE)) -> USA | O32: =IF(L32="","",VLOOKUP(L32,[1]ISO辞書!A:B,2,FALSE)) -> ISR | P32: =_xlfn.TEXTJOIN(";",TRUE,M32:O32) -> IRN;USA;ISR | Q32: 中東の戦火が海路に広がれば原油と輸送費が上がり、日本のエネルギー調達にも直結する。 | R32: 紛争 | S32: 46110 | T32: Reuters | U32: https://www.reuters.com/world/asia-pacific/yemens-houthis-enter-iran-war-with-attacks-israel-while-us-marines-arrive-region-2026-03-28/ | V32: 5
A33: =IF(C33="","",VLOOKUP(C33,[1]ISO辞書!A:C,2,FALSE)) -> UKR | B33: =IF(C33="","",VLOOKUP(C33,[1]ISO辞書!A:C,3,FALSE)) -> Ukraine | C33: ウクライナ | D33: ゼレンスキー大統領のヨルダン訪問 | E33: ウクライナのゼレンスキー大統領はヨルダンのアブドラ国王と会談し、ドローン攻撃への対処を含む安全保障協力を協議。中東・湾岸地域での支援拡大を狙う。 | J33: ヨルダン | M33: =IF(J33="","",VLOOKUP(J33,[1]ISO辞書!A:B,2,FALSE)) -> JOR | N33: =IF(K33="","",VLOOKUP(K33,[1]ISO辞書!A:B,2,FALSE)) | O33: =IF(L33="","",VLOOKUP(L33,[1]ISO辞書!A:B,2,FALSE)) | P33: =_xlfn.TEXTJOIN(";",TRUE,M33:O33) -> JOR | Q33: 湾岸諸国の関与が深まれば、ウクライナ支援の裾野が広がり、軍事技術協力の流れも変わる可能性。 | R33: 外交 | S33: 46110 | T33: Reuters | U33: https://www.reuters.com/business/aerospace-defense/ukraines-zelenskiy-arrives-jordan-next-leg-gulf-tour-2026-03-29/ | V33: 2
A34: =IF(C34="","",VLOOKUP(C34,[1]ISO辞書!A:C,2,FALSE)) -> EGY | B34: =IF(C34="","",VLOOKUP(C34,[1]ISO辞書!A:C,3,FALSE)) -> Egypt | C34: エジプト | D34: アラブ連盟の事務総長にエジプト外交官が指名される | E34: アラブ諸国の外相らは、エジプトの外交官であるファヒミ氏をアラブ連盟事務総長に全会一致で指名した。 | M34: =IF(J34="","",VLOOKUP(J34,[1]ISO辞書!A:B,2,FALSE)) | N34: =IF(K34="","",VLOOKUP(K34,[1]ISO辞書!A:B,2,FALSE)) | O34: =IF(L34="","",VLOOKUP(L34,[1]ISO辞書!A:B,2,FALSE)) | P34: =_xlfn.TEXTJOIN(";",TRUE,M34:O34) | Q34: 中東外交の調整役の交代により、ガザ地区やイランをめぐる地域対話の進め方に影響が出る。 | R34: 外交 | S34: 46110 | T34: Reuters | U34: https://www.reuters.com/business/media-telecom/arab-foreign-ministers-name-nabil-fahmy-arab-league-chief-2026-03-29/ | V34: 3
A35: =IF(C35="","",VLOOKUP(C35,[1]ISO辞書!A:C,2,FALSE)) -> CUB | B35: =IF(C35="","",VLOOKUP(C35,[1]ISO辞書!A:C,3,FALSE)) -> Cuba | C35: キューバ | D35: ロシア原油がキューバに到着 | E35: ロシアが燃料不足のキューバへ原油を輸送し、深刻な人道危機を一時的にしのいだ。アメリカは同国への輸送を認めており、制裁運用の見方が分かれている。 | J35: ロシア | K35: アメリカ | M35: =IF(J35="","",VLOOKUP(J35,[1]ISO辞書!A:B,2,FALSE)) -> RUS | N35: =IF(K35="","",VLOOKUP(K35,[1]ISO辞書!A:B,2,FALSE)) -> USA | O35: =IF(L35="","",VLOOKUP(L35,[1]ISO辞書!A:B,2,FALSE)) | P35: =_xlfn.TEXTJOIN(";",TRUE,M35:O35) -> RUS;USA | Q35: キューバの原油調達が滞れば同国の政権が動揺しかねない事態が起きうる。 | R35: エネルギー | S35: 46111 | T35: Bloomberg | U35: https://www.bloomberg.com/news/articles/2026-03-30/russian-oil-shipment-buys-us-and-cuba-time-as-crisis-festers | V35: 3
A36: =IF(C36="","",VLOOKUP(C36,[1]ISO辞書!A:C,2,FALSE)) -> LBN | B36: =IF(C36="","",VLOOKUP(C36,[1]ISO辞書!A:C,3,FALSE)) -> Lebanon | C36: レバノン | D36: レバノン南部で国連平和維持軍3名が死亡 | E36: レバノン南部で、インドネシア出身の国連平和維持部隊の兵士3人が死亡。イスラエル軍の攻撃が続く中、UNIFILの安全が改めて問われている。 | J36: イスラエル | M36: =IF(J36="","",VLOOKUP(J36,[1]ISO辞書!A:B,2,FALSE)) -> ISR | N36: =IF(K36="","",VLOOKUP(K36,[1]ISO辞書!A:B,2,FALSE)) | O36: =IF(L36="","",VLOOKUP(L36,[1]ISO辞書!A:B,2,FALSE)) | P36: =_xlfn.TEXTJOIN(";",TRUE,M36:O36) -> ISR | Q36: 国連平和維持軍への被害拡大は、レバノン情勢の悪化を示し、中東の緊張と不安を長引かせる。 | R36: 紛争 | S36: 46111 | T36: Reuters | U36: https://www.reuters.com/world/middle-east/unifil-says-one-peacekeeper-killed-one-critically-injured-southern-lebanon-2026-03-29/ | V36: 2
A37: =IF(C37="","",VLOOKUP(C37,[1]ISO辞書!A:C,2,FALSE)) -> RUS | B37: =IF(C37="","",VLOOKUP(C37,[1]ISO辞書!A:C,3,FALSE)) -> Russian Federation | C37: ロシア | D37: ロシアがスパイ容疑で英外交官を追放 | E37: ロシアは経済スパイ活動に関与したとしてイギリスの外交官を追放。イギリスは容認できないと強く反発した。 | J37: イギリス | M37: =IF(J37="","",VLOOKUP(J37,[1]ISO辞書!A:B,2,FALSE)) -> GBR | N37: =IF(K37="","",VLOOKUP(K37,[1]ISO辞書!A:B,2,FALSE)) | O37: =IF(L37="","",VLOOKUP(L37,[1]ISO辞書!A:B,2,FALSE)) | P37: =_xlfn.TEXTJOIN(";",TRUE,M37:O37) -> GBR | Q37: 英露の対立が続けば、ウクライナ戦争をめぐる欧州の緊張がさらに強まり、対露制裁の流れにも影響する。 | R37: 外交 | S37: 46111 | T37: Reuters | U37: https://www.reuters.com/world/russia-expels-british-diplomat-over-espionage-fsb-says-2026-03-30/ | V37: 2
A38: =IF(C38="","",VLOOKUP(C38,[1]ISO辞書!A:C,2,FALSE)) -> AFG | B38: =IF(C38="","",VLOOKUP(C38,[1]ISO辞書!A:C,3,FALSE)) -> Afghanistan | C38: アフガニスタン | D38: アフガニスタンとパキスタンで豪雨被害 | E38: アフガニスタンとパキスタンで豪雨と洪水が発生し、合わせて45人が死亡。アフガンでは約130棟の建物が倒壊し、パキスタンでも多くの子どもが犠牲になった。 | J38: パキスタン | M38: =IF(J38="","",VLOOKUP(J38,[1]ISO辞書!A:B,2,FALSE)) -> PAK | N38: =IF(K38="","",VLOOKUP(K38,[1]ISO辞書!A:B,2,FALSE)) | O38: =IF(L38="","",VLOOKUP(L38,[1]ISO辞書!A:B,2,FALSE)) | P38: =_xlfn.TEXTJOIN(";",TRUE,M38:O38) -> PAK | R38: 人道 | S38: 46111 | T38: Reuters | U38: https://www.reuters.com/sustainability/climate-energy/heavy-rain-floods-kill-22-people-afghanistan-2026-03-30/ | V38: 1
A39: =IF(C39="","",VLOOKUP(C39,[1]ISO辞書!A:C,2,FALSE)) -> XKK | B39: =IF(C39="","",VLOOKUP(C39,[1]ISO辞書!A:C,3,FALSE)) -> Kosovo | C39: コソボ | D39: コソボがガザ地区への部隊派遣を承認 | E39: コソボ政府は、アメリカ主導の平和評議会の一員として、ガザへの部隊派遣を承認した。ガザ地区における停戦後の治安維持と暫定統治を支える構想の一部となる。 | J39: アメリカ | K39: イスラエル | L39: パレスチナ | M39: =IF(J39="","",VLOOKUP(J39,[1]ISO辞書!A:B,2,FALSE)) -> USA | N39: =IF(K39="","",VLOOKUP(K39,[1]ISO辞書!A:B,2,FALSE)) -> ISR | O39: =IF(L39="","",VLOOKUP(L39,[1]ISO辞書!A:B,2,FALSE)) -> PSE | P39: =_xlfn.TEXTJOIN(";",TRUE,M39:O39) -> USA;ISR;PSE | R39: 紛争 | S39: 46111 | T39: Reuters | U39: https://www.reuters.com/world/asia-pacific/kosovo-approves-troops-gaza-under-us-backed-scheme-2026-03-30/ | V39: 2
A40: =IF(C40="","",VLOOKUP(C40,[1]ISO辞書!A:C,2,FALSE)) -> PAK | B40: =IF(C40="","",VLOOKUP(C40,[1]ISO辞書!A:C,3,FALSE)) -> Pakistan | C40: パキスタン | D40: パキスタンとアフガニスタンが再衝突 | E40: アフガニスタンとパキスタンとの間で、停戦期間中に重火器での交戦が発生し、国境地帯の緊張が再び高まった。 | J40: アフガニスタン | M40: =IF(J40="","",VLOOKUP(J40,[1]ISO辞書!A:B,2,FALSE)) -> AFG | N40: =IF(K40="","",VLOOKUP(K40,[1]ISO辞書!A:B,2,FALSE)) | O40: =IF(L40="","",VLOOKUP(L40,[1]ISO辞書!A:B,2,FALSE)) | P40: =_xlfn.TEXTJOIN(";",TRUE,M40:O40) -> AFG | Q40: 国境衝突が続けば地域貿易や物流が不安定化し、南アジアの安全保障にも悪影響が及ぶ。 | R40: 紛争 | S40: 46111 | T40: Reuters | U40: https://www.reuters.com/world/asia-pacific/pakistan-afghanistan-trade-fire-islamabad-prepares-host-us-iran-talks-2026-03-30/ | V40: 4
A41: =IF(C41="","",VLOOKUP(C41,[1]ISO辞書!A:C,2,FALSE)) -> USA | B41: =IF(C41="","",VLOOKUP(C41,[1]ISO辞書!A:C,3,FALSE)) -> America | C41: アメリカ | D41: アメリカがベネズエラの大使館を再開 | E41: アメリカはベネズエラの首都カラカスの大使館を正式に再開し、ベネズエラとの関係正常化を進めた。制裁緩和や投資の促進、ベネズエラ産原油の扱いが焦点になっている。 | J41: ベネズエラ | M41: =IF(J41="","",VLOOKUP(J41,[1]ISO辞書!A:B,2,FALSE)) -> VEN | N41: =IF(K41="","",VLOOKUP(K41,[1]ISO辞書!A:B,2,FALSE)) | O41: =IF(L41="","",VLOOKUP(L41,[1]ISO辞書!A:B,2,FALSE)) | P41: =_xlfn.TEXTJOIN(";",TRUE,M41:O41) -> VEN | Q41: 対ベネズエラ政策の変化は原油市場と制裁の運用に響き、日本のエネルギー価格にも間接的な影響を及ぼす。 | R41: 外交 | S41: 46111 | T41: Reuters | U41: https://www.reuters.com/world/americas/us-resumes-embassy-operations-venezuela-2026-03-30/ | V41: 3
A42: =IF(C42="","",VLOOKUP(C42,[1]ISO辞書!A:C,2,FALSE)) -> EGY | B42: =IF(C42="","",VLOOKUP(C42,[1]ISO辞書!A:C,3,FALSE)) -> Egypt | C42: エジプト | D42: エジプトとキプロス、天然ガス協力協定に署名 | E42: エジプトとキプロスは、キプロスのガス資源開発とエジプトへのガス供給を見据えた協力枠組みを締結。 | J42: キプロス | M42: =IF(J42="","",VLOOKUP(J42,[1]ISO辞書!A:B,2,FALSE)) -> CYP | N42: =IF(K42="","",VLOOKUP(K42,[1]ISO辞書!A:B,2,FALSE)) | O42: =IF(L42="","",VLOOKUP(L42,[1]ISO辞書!A:B,2,FALSE)) | P42: =_xlfn.TEXTJOIN(";",TRUE,M42:O42) -> CYP | Q42: LNGや海上輸送の安定化につながれば、日本のエネルギー調達にも追い風となる一方、同地域での資源開発を進めるトルコとの対立が気がかり。 | R42: エネルギー | S42: 46111 | T42: Reuters | U42: https://www.reuters.com/business/energy/egypt-cyprus-sign-framework-agreement-cooperation-gas-2026-03-30/ | V42: 3
A43: =IF(C43="","",VLOOKUP(C43,[1]ISO辞書!A:C,2,FALSE)) -> SOM | B43: =IF(C43="","",VLOOKUP(C43,[1]ISO辞書!A:C,3,FALSE)) -> Somalia | C43: ソマリア | D43: ソマリア軍が南西部主要都市を制圧 | E43: ソマリア国軍が南西州最大都市バイドアの制圧に動き、同州政府のラフタガレーン首相が辞任。ソマリア政府と地方との対立が改めて表面化した。 | M43: =IF(J43="","",VLOOKUP(J43,[1]ISO辞書!A:B,2,FALSE)) | N43: =IF(K43="","",VLOOKUP(K43,[1]ISO辞書!A:B,2,FALSE)) | O43: =IF(L43="","",VLOOKUP(L43,[1]ISO辞書!A:B,2,FALSE)) | P43: =_xlfn.TEXTJOIN(";",TRUE,M43:O43) | Q43: アフリカの角における治安悪化が続くことで、紅海における航路が不安定化する可能性。日本の資源調達や貿易面でも影響が生じうる。 | R43: 国内政治 | S43: 46111 | T43: Reuters | U43: https://www.reuters.com/world/africa/somali-national-army-takes-control-part-biggest-city-south-west-state-2026-03-30/ | V43: 4
A44: =IF(C44="","",VLOOKUP(C44,[1]ISO辞書!A:C,2,FALSE)) -> IRN | B44: =IF(C44="","",VLOOKUP(C44,[1]ISO辞書!A:C,3,FALSE)) -> Iran | C44: イラン | D44: イラン海軍司令官の死亡が発表される | E44: イランは、革命防衛隊の海軍司令官であるタンサリ氏の死亡を発表。イスラエルはすでに同司令官を攻撃で排除したと主張していた。 | J44: イスラエル | M44: =IF(J44="","",VLOOKUP(J44,[1]ISO辞書!A:B,2,FALSE)) -> ISR | N44: =IF(K44="","",VLOOKUP(K44,[1]ISO辞書!A:B,2,FALSE)) | O44: =IF(L44="","",VLOOKUP(L44,[1]ISO辞書!A:B,2,FALSE)) | P44: =_xlfn.TEXTJOIN(";",TRUE,M44:O44) -> ISR | Q44: イスラエルとイランの間での報復合戦が続き、地域の不安定化と原油市場への影響が危惧される。 | R44: 紛争 | S44: 46111 | T44: Reuters | U44: https://www.reuters.com/world/middle-east/iran-confirms-death-revolutionary-guards-navy-commander-tangsiri-statement-says-2026-03-30/ | V44: 4
A45: =IF(C45="","",VLOOKUP(C45,[1]ISO辞書!A:C,2,FALSE)) -> PRY | B45: =IF(C45="","",VLOOKUP(C45,[1]ISO辞書!A:C,3,FALSE)) -> Paraguay | C45: パラグアイ | D45: パラグアイ、財務相が交代 | E45: パラグアイのフェルナンデス財務相が辞任。ガレアノ氏が暫定財務相を務めることになった。 | M45: =IF(J45="","",VLOOKUP(J45,[1]ISO辞書!A:B,2,FALSE)) | N45: =IF(K45="","",VLOOKUP(K45,[1]ISO辞書!A:B,2,FALSE)) | O45: =IF(L45="","",VLOOKUP(L45,[1]ISO辞書!A:B,2,FALSE)) | P45: =_xlfn.TEXTJOIN(";",TRUE,M45:O45) | R45: 国内政治 | S45: 46112 | T45: Bloomberg | U45: https://www.bloomberg.com/news/articles/2026-03-31/paraguay-names-interim-finance-chief-after-fernandez-resigns | V45: 1
A46: =IF(C46="","",VLOOKUP(C46,[1]ISO辞書!A:C,2,FALSE)) -> USA | B46: =IF(C46="","",VLOOKUP(C46,[1]ISO辞書!A:C,3,FALSE)) -> America | C46: アメリカ | D46: アメリカ、3隻目の空母を中東海域へ派遣 | E46: 米海軍が3隻目の空母を中東地域へ派遣。イラン戦争の長期化に備える動きとみられる。 | J46: イラン | M46: =IF(J46="","",VLOOKUP(J46,[1]ISO辞書!A:B,2,FALSE)) -> IRN | N46: =IF(K46="","",VLOOKUP(K46,[1]ISO辞書!A:B,2,FALSE)) | O46: =IF(L46="","",VLOOKUP(L46,[1]ISO辞書!A:B,2,FALSE)) | P46: =_xlfn.TEXTJOIN(";",TRUE,M46:O46) -> IRN | Q46: 中東における軍事的圧力が強まれば海上輸送と原油価格の高騰が懸念される。 | R46: 紛争 | S46: 46112 | T46: Bloomberg | U46: https://www.bloomberg.com/news/articles/2026-03-31/third-us-aircraft-carrier-heads-to-mideast-as-iran-war-continues | V46: 5
A47: =IF(C47="","",VLOOKUP(C47,[1]ISO辞書!A:C,2,FALSE)) -> GBR | B47: =IF(C47="","",VLOOKUP(C47,[1]ISO辞書!A:C,3,FALSE)) -> Britain | C47: イギリス | D47: イギリスとシリアの首脳会談 | E47: 英スターマー首相は、ロンドンでシリアシャラア大統領と会談。移民対策や国境警備、密航組織への対応を協議した。 | J47: シリア | M47: =IF(J47="","",VLOOKUP(J47,[1]ISO辞書!A:B,2,FALSE)) -> SYR | N47: =IF(K47="","",VLOOKUP(K47,[1]ISO辞書!A:B,2,FALSE)) | O47: =IF(L47="","",VLOOKUP(L47,[1]ISO辞書!A:B,2,FALSE)) | P47: =_xlfn.TEXTJOIN(";",TRUE,M47:O47) -> SYR | Q47: イギリスとシリアの関係改善は、欧州の移民政策に影響し、中東情勢の安定にも関わる。 | R47: 外交 | S47: 46112 | T47: Reuters | U47: https://www.reuters.com/world/middle-east/uk-pm-starmer-raises-migration-border-security-talks-with-syrias-president-2026-03-31/ | V47: 3
A48: =IF(C48="","",VLOOKUP(C48,[1]ISO辞書!A:C,2,FALSE)) -> ISR | B48: =IF(C48="","",VLOOKUP(C48,[1]ISO辞書!A:C,3,FALSE)) -> Israel | C48: イスラエル | D48: イスラエルがレバノン南部に緩衝地帯設置を表明 | E48: イスラエルの国防相は、ヒズボラとの戦闘終結後も南レバノンのリタニ川までを緩衝地帯として管理すると表明。国境地帯の軍事支配を続ける方針。 | J48: レバノン | M48: =IF(J48="","",VLOOKUP(J48,[1]ISO辞書!A:B,2,FALSE)) -> LBN | N48: =IF(K48="","",VLOOKUP(K48,[1]ISO辞書!A:B,2,FALSE)) | O48: =IF(L48="","",VLOOKUP(L48,[1]ISO辞書!A:B,2,FALSE)) | P48: =_xlfn.TEXTJOIN(";",TRUE,M48:O48) -> LBN | Q48: レバノンの主権問題が深まれば中東の緊張が長引き、海運と原油市場を通じて日本にも影響する。 | R48: 紛争 | S48: 46112 | T48: Reuters | U48: https://www.reuters.com/world/middle-east/israel-establish-buffer-zone-south-lebanon-up-litani-river-defence-minister-says-2026-03-31/ | V48: 4
A49: =IF(C49="","",VLOOKUP(C49,[1]ISO辞書!A:C,2,FALSE)) -> ITA | B49: =IF(C49="","",VLOOKUP(C49,[1]ISO辞書!A:C,3,FALSE)) -> Italy | C49: イタリア | D49: イタリア、米軍機のシチリア基地利用を拒否と発表 | E49: イタリアは、中東へ向かう米軍機がシチリアのイタリア軍基地を利用することを拒否したと発表。 | J49: アメリカ | M49: =IF(J49="","",VLOOKUP(J49,[1]ISO辞書!A:B,2,FALSE)) -> USA | N49: =IF(K49="","",VLOOKUP(K49,[1]ISO辞書!A:B,2,FALSE)) | O49: =IF(L49="","",VLOOKUP(L49,[1]ISO辞書!A:B,2,FALSE)) | P49: =_xlfn.TEXTJOIN(";",TRUE,M49:O49) -> USA | Q49: これまで良好だったイタリアとアメリカの関係悪化が危惧される。 | R49: 外交 | S49: 46112 | T49: Reuters | U49: https://www.reuters.com/business/aerospace-defense/italy-refuses-us-aircraft-use-sicily-base-middle-east-operations-source-says-2026-03-31/ | V49: 3
A50: =IF(C50="","",VLOOKUP(C50,[1]ISO辞書!A:C,2,FALSE)) -> FRA | B50: =IF(C50="","",VLOOKUP(C50,[1]ISO辞書!A:C,3,FALSE)) -> France | C50: フランス | D50: フランスがイスラエルの領空通過を拒否 | E50: フランスは、イラン戦争で使用されるアメリカ製兵器の輸送に自国空域を使うようイスラエルが求めたが、これを拒否した。欧米諸国における足並みの乱れが目立つ。 | J50: イスラエル | K50: アメリカ | M50: =IF(J50="","",VLOOKUP(J50,[1]ISO辞書!A:B,2,FALSE)) -> ISR | N50: =IF(K50="","",VLOOKUP(K50,[1]ISO辞書!A:B,2,FALSE)) -> USA | O50: =IF(L50="","",VLOOKUP(L50,[1]ISO辞書!A:B,2,FALSE)) | P50: =_xlfn.TEXTJOIN(";",TRUE,M50:O50) -> ISR;USA | Q50: 欧州の空域管理が厳しくなれば軍事補給と外交の摩擦が増し、中東危機の長期化にもつながる。 | R50: 外交 | S50: 46112 | T50: Reuters | U50: https://www.reuters.com/world/china/france-refused-israel-use-its-air-space-transfer-us-weapons-iran-war-sources-2026-03-31/ | V50: 3
A51: =IF(C51="","",VLOOKUP(C51,[1]ISO辞書!A:C,2,FALSE)) -> THA | B51: =IF(C51="","",VLOOKUP(C51,[1]ISO辞書!A:C,3,FALSE)) -> Thailand | C51: タイ | D51: タイにて新内閣が承認される | E51: タイのワチラロンコン国王が、アヌティン首相の新内閣を承認した。 | M51: =IF(J51="","",VLOOKUP(J51,[1]ISO辞書!A:B,2,FALSE)) | N51: =IF(K51="","",VLOOKUP(K51,[1]ISO辞書!A:B,2,FALSE)) | O51: =IF(L51="","",VLOOKUP(L51,[1]ISO辞書!A:B,2,FALSE)) | P51: =_xlfn.TEXTJOIN(";",TRUE,M51:O51) | Q51: 政権が固まれば政策運営は安定し、東南アジアの対外経済や対中関係にも影響する。 | R51: 国内政治 | S51: 46112 | T51: Reuters | U51: https://www.reuters.com/world/asia-pacific/thai-king-approves-pm-anutins-cabinet-royal-gazette-says-2026-03-31/ | V51: 2
A52: =IF(C52="","",VLOOKUP(C52,[1]ISO辞書!A:C,2,FALSE)) -> KOR | B52: =IF(C52="","",VLOOKUP(C52,[1]ISO辞書!A:C,3,FALSE)) -> Korea | C52: 韓国 | D52: 韓国にて株価の大暴落と通貨の急落が発生 | E52: 韓国市場で株価の大暴落と通貨の急落が発生。同国通貨のウォンは1ドル＝1500ウォンを割る水準まで売られた。 | M52: =IF(J52="","",VLOOKUP(J52,[1]ISO辞書!A:B,2,FALSE)) | N52: =IF(K52="","",VLOOKUP(K52,[1]ISO辞書!A:B,2,FALSE)) | O52: =IF(L52="","",VLOOKUP(L52,[1]ISO辞書!A:B,2,FALSE)) | P52: =_xlfn.TEXTJOIN(";",TRUE,M52:O52) | Q52: 世界的なリスク回避が強まると、アジア市場の連鎖安や為替変動が起きやすい。日本の輸出企業や金融市場にも間接的に波及する。 | R52: 金融 | S52: 46112 | T52: Reuters | U52: https://www.reuters.com/world/asia-pacific/south-korea-hit-by-steepest-stocks-selloff-since-2008-currency-tumbles-2026-03-31/ | V52: 4
A53: =IF(C53="","",VLOOKUP(C53,[1]ISO辞書!A:C,2,FALSE)) -> MNG | B53: =IF(C53="","",VLOOKUP(C53,[1]ISO辞書!A:C,3,FALSE)) -> Mongolia | C53: モンゴル | D53: モンゴルにて新首相が承認される | E53: モンゴル議会は、ニャムオソル氏を新首相に選出した。与党内対立と議会の行き詰まりで前首相が辞任し、9カ月で3人目の首相交代となった。 | M53: =IF(J53="","",VLOOKUP(J53,[1]ISO辞書!A:B,2,FALSE)) | N53: =IF(K53="","",VLOOKUP(K53,[1]ISO辞書!A:B,2,FALSE)) | O53: =IF(L53="","",VLOOKUP(L53,[1]ISO辞書!A:B,2,FALSE)) | P53: =_xlfn.TEXTJOIN(";",TRUE,M53:O53) | Q53: 政権交代が続くことで資源国であるモンゴルの投資環境は不安定になりやすい。中国や日本を含む周辺国との経済関係にも影響する。 | R53: 国内政治 | S53: 46112 | T53: Reuters | U53: https://www.reuters.com/world/china/mongolia-names-new-prime-minister-following-stalemate-parliament-2026-03-31/ | V53: 1
A54: =IF(C54="","",VLOOKUP(C54,[1]ISO辞書!A:C,2,FALSE)) -> DEU | B54: =IF(C54="","",VLOOKUP(C54,[1]ISO辞書!A:C,3,FALSE)) -> Germany | C54: ドイツ | D54: ドイツ極右政党、ロシアとの関係修復を主張 | E54: 燃料価格の高騰を背景に、ドイツの極右政党「ドイツのための選択肢」が、安いロシア産エネルギーを調達すべきだと主張。アメリカとイスラエルの対イラン戦争後、ガソリン価格は15％超上昇している。 | M54: =IF(J54="","",VLOOKUP(J54,[1]ISO辞書!A:B,2,FALSE)) | N54: =IF(K54="","",VLOOKUP(K54,[1]ISO辞書!A:B,2,FALSE)) | O54: =IF(L54="","",VLOOKUP(L54,[1]ISO辞書!A:B,2,FALSE)) | P54: =_xlfn.TEXTJOIN(";",TRUE,M54:O54) | Q54: ロシアとの関係改善の声が強まることで、ウクライナ支援の足並みが乱れる懸念。 | R54: 国内政治 | S54: 46112 | T54: Reuters | U54: https://www.reuters.com/business/soaring-fuel-prices-drive-german-far-right-calls-turn-back-russia-2026-03-31/ | V54: 3
A55: =IF(C55="","",VLOOKUP(C55,[1]ISO辞書!A:C,2,FALSE)) -> SRB | B55: =IF(C55="","",VLOOKUP(C55,[1]ISO辞書!A:C,3,FALSE)) -> Serbia | C55: セルビア | D55: セルビア首都での大規模抗議活動 | E55: セルビアの首都ベオグラードで、大学事務所の家宅捜索に抗議する学生らと警察が衝突。学生が死亡した事件をめぐる一連の捜査が、反政府運動への反発を強めた。 | M55: =IF(J55="","",VLOOKUP(J55,[1]ISO辞書!A:B,2,FALSE)) | N55: =IF(K55="","",VLOOKUP(K55,[1]ISO辞書!A:B,2,FALSE)) | O55: =IF(L55="","",VLOOKUP(L55,[1]ISO辞書!A:B,2,FALSE)) | P55: =_xlfn.TEXTJOIN(";",TRUE,M55:O55) | Q55: 抗議の激化は、セルビアの政治不安を長引かせる。西バルカン地域の安定が揺らげば、欧州全体の安定にも影響する。 | R55: 国内政治 | S55: 46112 | T55: Reuters | U55: https://www.reuters.com/world/serbian-students-protesters-clash-with-police-belgrade-2026-03-31/ | V55: 3
A56: =IF(C56="","",VLOOKUP(C56,[1]ISO辞書!A:C,2,FALSE)) -> SYR | B56: =IF(C56="","",VLOOKUP(C56,[1]ISO辞書!A:C,3,FALSE)) -> Syrian Arab Republic | C56: シリア | D56: シリア暫定大統領がイラン紛争不干渉を表明 | E56: シリアのシャラア大統領は、シリアが攻撃を受けない限り、アメリカとイスラエルの対イラン戦争に加わらないと述べた。中東の戦火拡大を避けたい姿勢を示した。 | J56: イラン | K56: アメリカ | L56: イスラエル | M56: =IF(J56="","",VLOOKUP(J56,[1]ISO辞書!A:B,2,FALSE)) -> IRN | N56: =IF(K56="","",VLOOKUP(K56,[1]ISO辞書!A:B,2,FALSE)) -> USA | O56: =IF(L56="","",VLOOKUP(L56,[1]ISO辞書!A:B,2,FALSE)) -> ISR | P56: =_xlfn.TEXTJOIN(";",TRUE,M56:O56) -> IRN;USA;ISR | Q56: シリアが中立を保てば戦線拡大は抑えやすいが、地域全体の緊張はなお高いまま。テロ組織による活動でシリアが被害を受ける懸念も。 | R56: 外交 | S56: 46112 | T56: Reuters | U56: https://www.reuters.com/world/europe/syria-will-stay-out-iran-conflict-unless-it-faces-aggression-president-says-2026-03-31/ | V56: 3
A57: =IF(C57="","",VLOOKUP(C57,[1]ISO辞書!A:C,2,FALSE)) -> USA | B57: =IF(C57="","",VLOOKUP(C57,[1]ISO辞書!A:C,3,FALSE)) -> America | C57: アメリカ | D57: 米トランプ大統領がNATO脱退を仄めかす | E57: トランプ大統領は、欧州の同盟国がホルムズ海峡封鎖解除に協力しないことを理由に、NATO離脱を検討していると発言。欧米諸国の同盟関係に緊張が走った。 | M57: =IF(J57="","",VLOOKUP(J57,[1]ISO辞書!A:B,2,FALSE)) | N57: =IF(K57="","",VLOOKUP(K57,[1]ISO辞書!A:B,2,FALSE)) | O57: =IF(L57="","",VLOOKUP(L57,[1]ISO辞書!A:B,2,FALSE)) | P57: =_xlfn.TEXTJOIN(";",TRUE,M57:O57) | Q57: NATOの結束が揺らげば、中東の安全保障と海上輸送の不安が増すほか、対ロシア政策にも影響が生じる。 | S57: 46113 | T57: Reuters | U57: https://www.reuters.com/business/aerospace-defense/trump-threatens-nato-exit-scaling-up-tensions-with-allies-2026-04-01/ | V57: 4
A58: =IF(C58="","",VLOOKUP(C58,[1]ISO辞書!A:C,2,FALSE)) -> LBN | B58: =IF(C58="","",VLOOKUP(C58,[1]ISO辞書!A:C,3,FALSE)) -> Lebanon | C58: レバノン | D58: イスラエル空爆でヒズボラ最高司令官が死亡 | E58: イスラエル軍は、レバノンの首都ベイルートでヒズボラの司令官ハシェム氏を殺害したと発表。ヒズボラも死亡を認め、再び大きな打撃となった。 | J58: イスラエル | M58: =IF(J58="","",VLOOKUP(J58,[1]ISO辞書!A:B,2,FALSE)) -> ISR | N58: =IF(K58="","",VLOOKUP(K58,[1]ISO辞書!A:B,2,FALSE)) | O58: =IF(L58="","",VLOOKUP(L58,[1]ISO辞書!A:B,2,FALSE)) | P58: =_xlfn.TEXTJOIN(";",TRUE,M58:O58) -> ISR | Q58: レバノン情勢がさらに悪化すれば、中東の報復連鎖が長引く。原油相場や海運の不安定化は日本にも響く。 | R58: 紛争 | S58: 46113 | T58: Reuters | U58: https://www.reuters.com/world/middle-east/israeli-military-says-strike-beirut-killed-hezbollah-southern-front-commander-2026-04-01/ | V58: 4
A59: =IF(C59="","",VLOOKUP(C59,[1]ISO辞書!A:C,2,FALSE)) -> ARG | B59: =IF(C59="","",VLOOKUP(C59,[1]ISO辞書!A:C,3,FALSE)) -> Argentina | C59: アルゼンチン | D59: アルゼンチンがイラン革命防衛隊をテロ組織に指定 | E59: アルゼンチンは、イランの革命防衛隊をテロ組織に指定した。アメリカの圧力を受けた措置で、革命防衛隊に対する金融制裁などの運用が可能になる。 | J59: イラン | M59: =IF(J59="","",VLOOKUP(J59,[1]ISO辞書!A:B,2,FALSE)) -> IRN | N59: =IF(K59="","",VLOOKUP(K59,[1]ISO辞書!A:B,2,FALSE)) | O59: =IF(L59="","",VLOOKUP(L59,[1]ISO辞書!A:B,2,FALSE)) | P59: =_xlfn.TEXTJOIN(";",TRUE,M59:O59) -> IRN | Q59: 対イラン包囲が広がれば、国際的な制裁網はさらに強まる。中東地域の緊張と資源市場の不安定化が続きやすい。 | R59: 外交 | S59: 46113 | T59: Reuters | U59: https://www.reuters.com/world/middle-east/argentina-designates-irans-irgc-terrorist-organization-aligning-with-us-2026-04-01/ | V59: 4
A60: =IF(C60="","",VLOOKUP(C60,[1]ISO辞書!A:C,2,FALSE)) -> EU | B60: =IF(C60="","",VLOOKUP(C60,[1]ISO辞書!A:C,3,FALSE)) -> EU | C60: 欧州連合 | D60: EUがキューバへ230万ドルを人道支援として拠出 | E60: 欧州委員会は、深刻化する人道危機に対応するためにキューバへ追加の200万ユーロの支援を発表。燃料不足による停電と生活悪化が背景にある。 | J60: キューバ | M60: =IF(J60="","",VLOOKUP(J60,[1]ISO辞書!A:B,2,FALSE)) -> CUB | N60: =IF(K60="","",VLOOKUP(K60,[1]ISO辞書!A:B,2,FALSE)) | O60: =IF(L60="","",VLOOKUP(L60,[1]ISO辞書!A:B,2,FALSE)) | P60: =_xlfn.TEXTJOIN(";",TRUE,M60:O60) -> CUB | Q60: 支援はキューバにおける当面の食料・水不足を和らげるが、エネルギー危機は依然として継続中。 | R60: 外交 | S60: 46113 | T60: Reuters | U60: https://www.reuters.com/world/americas/eu-announces-further-23-million-humanitarian-aid-cuba-2026-04-01/ | V60: 3
A61: =IF(C61="","",VLOOKUP(C61,[1]ISO辞書!A:C,2,FALSE)) -> TCD | B61: =IF(C61="","",VLOOKUP(C61,[1]ISO辞書!A:C,3,FALSE)) -> Chad | C61: チャド | D61: チャドの先遣隊と国連の支援部隊がハイチに到着 | E61: 国連の治安部隊の新指揮官がハイチ入りし、チャド軍の先遣隊も同国へ到着した。首都圏で横行するギャング対策を立て直す局面に入った。 | J61: ハイチ | M61: =IF(J61="","",VLOOKUP(J61,[1]ISO辞書!A:B,2,FALSE)) -> HTI | N61: =IF(K61="","",VLOOKUP(K61,[1]ISO辞書!A:B,2,FALSE)) | O61: =IF(L61="","",VLOOKUP(L61,[1]ISO辞書!A:B,2,FALSE)) | P61: =_xlfn.TEXTJOIN(";",TRUE,M61:O61) -> HTI | R61: 紛争 | S61: 46113 | T61: Reuters | U61: https://www.reuters.com/world/americas/chadian-forces-arrive-haiti-fight-gangs-part-new-un-backed-force-2026-04-01/ | V61: 3
A62: =IF(C62="","",VLOOKUP(C62,[1]ISO辞書!A:C,2,FALSE)) -> RUS | B62: =IF(C62="","",VLOOKUP(C62,[1]ISO辞書!A:C,3,FALSE)) -> Russian Federation | C62: ロシア | D62: ロ軍がハリコフへドローン攻撃を継続 | E62: ロシア軍はウクライナ第2の都市ハルキウへの無人機攻撃を丸1日続け、少なくとも2人が負傷した。ザポリージャ原発でも被害が出たとの報告あり。 | J62: ウクライナ | M62: =IF(J62="","",VLOOKUP(J62,[1]ISO辞書!A:B,2,FALSE)) -> UKR | N62: =IF(K62="","",VLOOKUP(K62,[1]ISO辞書!A:B,2,FALSE)) | O62: =IF(L62="","",VLOOKUP(L62,[1]ISO辞書!A:B,2,FALSE)) | P62: =_xlfn.TEXTJOIN(";",TRUE,M62:O62) -> UKR | R62: 紛争 | S62: 46114 | T62: Reuters | U62: https://www.reuters.com/world/russian-forces-maintain-day-long-drone-barrage-ukraines-kharkiv-2026-04-02/ | V62: 4
A63: =IF(C63="","",VLOOKUP(C63,[1]ISO辞書!A:C,2,FALSE)) -> GBR | B63: =IF(C63="","",VLOOKUP(C63,[1]ISO辞書!A:C,3,FALSE)) -> Britain | C63: イギリス | D63: ホルムズ海峡封鎖問題に40カ国が協議 | E63: イギリスは、イランによるホルムズ海峡封鎖からの再開に向け、約40カ国が協調策を協議したと発表した。軍事・外交の両面で対応を探る。 | J63: ドイツ | K63: フランス | L63: UAE | M63: =IF(J63="","",VLOOKUP(J63,[1]ISO辞書!A:B,2,FALSE)) -> DEU | N63: =IF(K63="","",VLOOKUP(K63,[1]ISO辞書!A:B,2,FALSE)) -> FRA | O63: =IF(L63="","",VLOOKUP(L63,[1]ISO辞書!A:B,2,FALSE)) -> ARE | P63: =_xlfn.TEXTJOIN(";",TRUE,M63:O63) -> DEU;FRA;ARE | Q63: ホルムズ海峡の封鎖は原油とLNGの供給を直撃する。アメリカを除く同盟関係が進むことであらたな国際秩序の形成も期待。 | R63: エネルギー | S63: 46114 | T63: Reuters | U63: https://www.reuters.com/business/energy/dozens-countries-discuss-coalition-secure-passage-through-strait-hormuz-2026-04-02/ | V63: 5
A64: =IF(C64="","",VLOOKUP(C64,[1]ISO辞書!A:C,2,FALSE)) -> BFA | B64: =IF(C64="","",VLOOKUP(C64,[1]ISO辞書!A:C,3,FALSE)) -> Burkina Faso | C64: ブルキナファソ | D64: ブルキナファソ軍による民間人犠牲増報告 | E64: 人権団体の集計では、ブルキナファソとマリで政府軍と同盟勢力による民間人への被害や殺害件数が、テロ組織によるものを上回っていると発表される。 | J64: マリ | M64: =IF(J64="","",VLOOKUP(J64,[1]ISO辞書!A:B,2,FALSE)) -> MLI | N64: =IF(K64="","",VLOOKUP(K64,[1]ISO辞書!A:B,2,FALSE)) | O64: =IF(L64="","",VLOOKUP(L64,[1]ISO辞書!A:B,2,FALSE)) | P64: =_xlfn.TEXTJOIN(";",TRUE,M64:O64) -> MLI | Q64: アフリカのサヘル地域における治安悪化は、アフリカから欧州への難民増加と対外支援の長期化につながる。 | R64: 紛争 | S64: 46114 | T64: Reuters | U64: https://www.reuters.com/world/africa/burkina-mali-troops-kill-more-civilians-than-jihadists-do-data-shows-2026-04-02/ | V64: 3
A65: =IF(C65="","",VLOOKUP(C65,[1]ISO辞書!A:C,2,FALSE)) -> COD | B65: =IF(C65="","",VLOOKUP(C65,[1]ISO辞書!A:C,3,FALSE)) -> Democratic Republic of the Congo | C65: コンゴ民主共和国 | D65: DRコンゴ東部でIS系反乱が15人殺害 | E65: コンゴ民主共和国の東部で、IS系の反政府勢力による襲撃が発生。軍発表で43人が死亡した。 | M65: =IF(J65="","",VLOOKUP(J65,[1]ISO辞書!A:B,2,FALSE)) | N65: =IF(K65="","",VLOOKUP(K65,[1]ISO辞書!A:B,2,FALSE)) | O65: =IF(L65="","",VLOOKUP(L65,[1]ISO辞書!A:B,2,FALSE)) | P65: =_xlfn.TEXTJOIN(";",TRUE,M65:O65) | Q65: 鉱物資源地帯の治安悪化は世界的な供給網を動揺させる。特にバッテリーの原料に影響の出る可能性。 | R65: 紛争 | S65: 46114 | T65: Reuters | U65: https://www.reuters.com/world/africa/islamic-state-linked-rebels-kill-15-eastern-congo-officials-say-2026-04-02/ | V65: 2
A66: =IF(C66="","",VLOOKUP(C66,[1]ISO辞書!A:C,2,FALSE)) -> USA | B66: =IF(C66="","",VLOOKUP(C66,[1]ISO辞書!A:C,3,FALSE)) -> America | C66: アメリカ | D66: アメリカがベネズエラ暫定大統領への制裁を解除 | E66: アメリカ政府はベネズエラの暫定大統領であるロドリゲス氏への制裁を解除した。対ベネズエラ制裁の緩和と関係改善が進行。 | J66: ベネズエラ | M66: =IF(J66="","",VLOOKUP(J66,[1]ISO辞書!A:B,2,FALSE)) -> VEN | N66: =IF(K66="","",VLOOKUP(K66,[1]ISO辞書!A:B,2,FALSE)) | O66: =IF(L66="","",VLOOKUP(L66,[1]ISO辞書!A:B,2,FALSE)) | P66: =_xlfn.TEXTJOIN(";",TRUE,M66:O66) -> VEN | Q66: 長年のベネズエラ制裁が緩和し国内情勢が改善されることで、北米を目指す移民数の削減も期待。 | R66: 外交 | S66: 46114 | T66: Reuters | U66: https://www.reuters.com/world/americas/us-lifts-sanctions-venezuelas-interim-president-2026-04-01/ | V66: 4
A67: =IF(C67="","",VLOOKUP(C67,[1]ISO辞書!A:C,2,FALSE)) -> NZL | B67: =IF(C67="","",VLOOKUP(C67,[1]ISO辞書!A:C,3,FALSE)) -> New Zealand | C67: ニュージーランド | D67: ニュージーランドとクック諸島が安全保障宣言に署名 | E67: ニュージーランドとクック諸島は防衛・安全保障を深化させることを発表。中国による太平洋地域への影響量拡大をめぐる動きと言える。 | J67: クック諸島 | M67: =IF(J67="","",VLOOKUP(J67,[1]ISO辞書!A:B,2,FALSE)) -> COK | N67: =IF(K67="","",VLOOKUP(K67,[1]ISO辞書!A:B,2,FALSE)) | O67: =IF(L67="","",VLOOKUP(L67,[1]ISO辞書!A:B,2,FALSE)) | P67: =_xlfn.TEXTJOIN(";",TRUE,M67:O67) -> COK | Q67: 太平洋の島嶼国における安全保障枠組みの再編は中国の影響力拡大と結びつく。アメリカ、オーストラリア、フィリピン、日本などの動きも注視する必要あり。 | R67: 外交 | S67: 46114 | T67: Reuters | U67: https://www.reuters.com/world/asia-pacific/new-zealand-cook-islands-sign-defence-security-declaration-2026-04-01/ | V67: 4
A68: =IF(C68="","",VLOOKUP(C68,[1]ISO辞書!A:C,2,FALSE)) -> IND | B68: =IF(C68="","",VLOOKUP(C68,[1]ISO辞書!A:C,3,FALSE)) -> India | C68: インド | D68: インド、英国主導のホルムズ海峡再開に向けた協議へ参加表明 | E68: インドは、イギリス主導のホルムズ海峡の再開策を探る協議に参加すると表明。 | J68: イギリス | K68: イラン | M68: =IF(J68="","",VLOOKUP(J68,[1]ISO辞書!A:B,2,FALSE)) -> GBR | N68: =IF(K68="","",VLOOKUP(K68,[1]ISO辞書!A:B,2,FALSE)) -> IRN | O68: =IF(L68="","",VLOOKUP(L68,[1]ISO辞書!A:B,2,FALSE)) | P68: =_xlfn.TEXTJOIN(";",TRUE,M68:O68) -> GBR;IRN | Q68: インドから近いイランにおける紛争や海峡封鎖はインド経済への影響が危惧される。同国が海峡封鎖解除への関与を強めることで、海上輸送の安定化に向けた国際連携が広がる可能性。 | R68: 外交 | S68: 46114 | T68: Bloomberg | U68: https://www.bloomberg.com/news/articles/2026-04-02/india-to-participate-in-uk-led-initiative-to-reopen-hormuz?srnd=phx-politics | V68: 4
A69: =IF(C69="","",VLOOKUP(C69,[1]ISO辞書!A:C,2,FALSE)) -> RUS | B69: =IF(C69="","",VLOOKUP(C69,[1]ISO辞書!A:C,3,FALSE)) -> Russian Federation | C69: ロシア | D69: ロシアがマダガスカル軍への武器供給強化と報道 | E69: ロシアはマダガスカルの軍事政権に装甲車や弾薬などを供与し、軍事関係を深めた。 | J69: マダガスカル | M69: =IF(J69="","",VLOOKUP(J69,[1]ISO辞書!A:B,2,FALSE)) -> MDG | N69: =IF(K69="","",VLOOKUP(K69,[1]ISO辞書!A:B,2,FALSE)) | O69: =IF(L69="","",VLOOKUP(L69,[1]ISO辞書!A:B,2,FALSE)) | P69: =_xlfn.TEXTJOIN(";",TRUE,M69:O69) -> MDG | Q69: アフリカでのロシアの関与拡大は、アフリカにおける勢力図を動かし、日本のアフリカ投資にも影響しうる。 | R69: 外交 | S69: 46114 | T69: Bloomberg | U69: https://www.bloomberg.com/news/articles/2026-04-02/russia-steps-up-arms-supplies-to-madagascar-s-military?srnd=phx-politics | V69: 3
A70: =IF(C70="","",VLOOKUP(C70,[1]ISO辞書!A:C,2,FALSE)) -> ITA | B70: =IF(C70="","",VLOOKUP(C70,[1]ISO辞書!A:C,3,FALSE)) -> Italy | C70: イタリア | D70: 伊メローニ首相の中東訪問 | E70: イタリアのメローニ首相が湾岸諸国への歴訪を実施。エネルギー安全保障と投資維持を訴えた。中東危機で燃料高が続く中、原油供給元の確保が急がれている。 | J70: サウジアラビア | K70: カタール | L70: UAE | M70: =IF(J70="","",VLOOKUP(J70,[1]ISO辞書!A:B,2,FALSE)) -> SAU | N70: =IF(K70="","",VLOOKUP(K70,[1]ISO辞書!A:B,2,FALSE)) -> QAT | O70: =IF(L70="","",VLOOKUP(L70,[1]ISO辞書!A:B,2,FALSE)) -> ARE | P70: =_xlfn.TEXTJOIN(";",TRUE,M70:O70) -> SAU;QAT;ARE | Q70: 欧州のエネルギー調達不安が続けばLNG市場が逼迫し、日本でも更なる価格高騰リスクの可能性。 | R70: 外交 | S70: 46115 | T70: Reuters | U70: https://www.reuters.com/world/europe/italys-meloni-flies-gulf-region-energy-security-push-2026-04-03/ | V70: 3
A71: =IF(C71="","",VLOOKUP(C71,[1]ISO辞書!A:C,2,FALSE)) -> KOR | B71: =IF(C71="","",VLOOKUP(C71,[1]ISO辞書!A:C,3,FALSE)) -> Korea | C71: 韓国 | D71: 韓国とフランスの首脳会談 | E71: 韓国とフランスの首脳会談が行われ、防衛とエネルギー分野を中心に協力を深めることで一致。 | J71: フランス | M71: =IF(J71="","",VLOOKUP(J71,[1]ISO辞書!A:B,2,FALSE)) -> FRA | N71: =IF(K71="","",VLOOKUP(K71,[1]ISO辞書!A:B,2,FALSE)) | O71: =IF(L71="","",VLOOKUP(L71,[1]ISO辞書!A:B,2,FALSE)) | P71: =_xlfn.TEXTJOIN(";",TRUE,M71:O71) -> FRA | R71: 外交 | S71: 46115 | T71: Reuters | U71: https://www.reuters.com/world/asia-pacific/south-korea-france-upgrade-ties-strategic-partnership-blue-house-says-2026-04-03/ | V71: 3
A72: =IF(C72="","",VLOOKUP(C72,[1]ISO辞書!A:C,2,FALSE)) -> RUS | B72: =IF(C72="","",VLOOKUP(C72,[1]ISO辞書!A:C,3,FALSE)) -> Russian Federation | C72: ロシア | D72: ロシアとトルコ首脳の電話会談 | E72: ロシアのプーチン大統領は、トルコのエルドアン大統領と電話会談し、中東情勢を協議した。詳細は示されなかったが、調停役としてのトルコの存在感が強まっている | J72: トルコ | M72: =IF(J72="","",VLOOKUP(J72,[1]ISO辞書!A:B,2,FALSE)) -> TUR | N72: =IF(K72="","",VLOOKUP(K72,[1]ISO辞書!A:B,2,FALSE)) | O72: =IF(L72="","",VLOOKUP(L72,[1]ISO辞書!A:B,2,FALSE)) | P72: =_xlfn.TEXTJOIN(";",TRUE,M72:O72) -> TUR | Q72: トルコが仲介役を保てれば、中東の軍事拡大を抑える余地が残り、原油市場の不安定化を和らげうる。 | R72: 外交 | S72: 46115 | T72: Reuters | U72: https://www.reuters.com/world/middle-east/putin-holds-call-with-turkeys-erdogan-discuss-middle-east-2026-04-03/ | V72: 4
A73: =IF(C73="","",VLOOKUP(C73,[1]ISO辞書!A:C,2,FALSE)) -> JPN | B73: =IF(C73="","",VLOOKUP(C73,[1]ISO辞書!A:C,3,FALSE)) -> Japan | C73: 日本 | D73: 日本等3カ国の船舶がホルムズ海峡を通過 | E73: 三井商船が共同保有するLNG船がホルムズ海峡を通過し、日本関連の船として初めて危機後に航行した。 | J73: フランス | K73: オマーン | L73: イラン | M73: =IF(J73="","",VLOOKUP(J73,[1]ISO辞書!A:B,2,FALSE)) -> FRA | N73: =IF(K73="","",VLOOKUP(K73,[1]ISO辞書!A:B,2,FALSE)) -> OMN | O73: =IF(L73="","",VLOOKUP(L73,[1]ISO辞書!A:B,2,FALSE)) -> IRN | P73: =_xlfn.TEXTJOIN(";",TRUE,M73:O73) -> FRA;OMN;IRN | Q73: 日本のLNG調達に直結する動きで、海峡の安全確保と輸送再開の見通しを左右する。 | R73: エネルギー | S73: 46115 | T73: Reuters | U73: https://www.reuters.com/business/energy/japanese-owned-lng-tanker-crosses-strait-hormuz-2026-04-03/ | V73: 4
A74: =IF(C74="","",VLOOKUP(C74,[1]ISO辞書!A:C,2,FALSE)) -> ETH | B74: =IF(C74="","",VLOOKUP(C74,[1]ISO辞書!A:C,3,FALSE)) -> Ethiopia | C74: エチオピア | D74: エチオピアと中国が債務問題で合意 | E74: エチオピアは中国との間で債務処理の整理で合意し、G20共通枠組みに沿った二国間交渉を前進させた。 | J74: 中国 | M74: =IF(J74="","",VLOOKUP(J74,[1]ISO辞書!A:B,2,FALSE)) -> CHN | N74: =IF(K74="","",VLOOKUP(K74,[1]ISO辞書!A:B,2,FALSE)) | O74: =IF(L74="","",VLOOKUP(L74,[1]ISO辞書!A:B,2,FALSE)) | P74: =_xlfn.TEXTJOIN(";",TRUE,M74:O74) -> CHN | Q74: 債務再編が進むことで東アフリカの投資環境改善が期待されるも、アフリカにおける中国進出がより強まっている。 | R74: 経済 | S74: 46115 | T74: Reuters | U74: https://www.reuters.com/world/africa/ethiopia-says-reaches-resolution-with-china-debt-treatment-2026-04-03/ | V74: 3
A75: =IF(C75="","",VLOOKUP(C75,[1]ISO辞書!A:C,2,FALSE)) -> CHN | B75: =IF(C75="","",VLOOKUP(C75,[1]ISO辞書!A:C,3,FALSE)) -> China | C75: 中国 | D75: 中国がデジタルヒューマンへの規制を強化 | E75: 中国当局は、デジタルヒューマンのルールなどの草案を公表した。子ども向けの依存性サービスにも制限をかける。 | M75: =IF(J75="","",VLOOKUP(J75,[1]ISO辞書!A:B,2,FALSE)) | N75: =IF(K75="","",VLOOKUP(K75,[1]ISO辞書!A:B,2,FALSE)) | O75: =IF(L75="","",VLOOKUP(L75,[1]ISO辞書!A:B,2,FALSE)) | P75: =_xlfn.TEXTJOIN(";",TRUE,M75:O75) | Q75: 生成AIの規制強化は、中国発のプラットフォームや広告事業に影響し、日本のAI規制議論にも参考になる。 | R75: 国内政治 | S75: 46115 | T75: Reuters | U75: https://www.reuters.com/world/china/china-moves-regulate-digital-humans-bans-addictive-services-children-2026-04-03/ | V75: 3
A76: =IF(C76="","",VLOOKUP(C76,[1]ISO辞書!A:C,2,FALSE)) -> RUS | B76: =IF(C76="","",VLOOKUP(C76,[1]ISO辞書!A:C,3,FALSE)) -> Russian Federation | C76: ロシア | D76: ロシア、国連安保理にてホルムズ海峡の航行再開に向けた動きを非難 | J76: イラン | K76: アメリカ | M76: =IF(J76="","",VLOOKUP(J76,[1]ISO辞書!A:B,2,FALSE)) -> IRN | N76: =IF(K76="","",VLOOKUP(K76,[1]ISO辞書!A:B,2,FALSE)) -> USA | O76: =IF(L76="","",VLOOKUP(L76,[1]ISO辞書!A:B,2,FALSE)) | P76: =_xlfn.TEXTJOIN(";",TRUE,M76:O76) -> IRN;USA | Q76: 地域情勢が不安定化 | R76: 紛争 | S76: 46115 | T76: Bloomberg | U76: https://www.bloomberg.com/news/articles/2026-04-03/russia-dismisses-push-at-un-to-force-open-the-strait-of-hormuz?srnd=phx-politics | V76: 4
A77: =IF(C77="","",VLOOKUP(C77,[1]ISO辞書!A:C,2,FALSE)) -> MMR | B77: =IF(C77="","",VLOOKUP(C77,[1]ISO辞書!A:C,3,FALSE)) -> Myanmar | C77: ミャンマー | D77: ミャンマーの大統領選挙 | E77: ミャンマーで軍事政権トップのミンアウンフライン氏が大統領に選出され、軍主導体制が制度上も固まった。 | M77: =IF(J77="","",VLOOKUP(J77,[1]ISO辞書!A:B,2,FALSE)) | N77: =IF(K77="","",VLOOKUP(K77,[1]ISO辞書!A:B,2,FALSE)) | O77: =IF(L77="","",VLOOKUP(L77,[1]ISO辞書!A:B,2,FALSE)) | P77: =_xlfn.TEXTJOIN(";",TRUE,M77:O77) | Q77: 民政移管はさらに遠のき、軍政の固定化は内戦と難民流出を長引かせうる。 | R77: 国内政治 | S77: 46115 | T77: Bloomberg | U77: https://www.bloomberg.com/news/articles/2026-04-03/myanmar-junta-retains-power-after-its-chief-wins-the-presidency?srnd=phx-politics | V77: 2
A78: =IF(C78="","",VLOOKUP(C78,[1]ISO辞書!A:C,2,FALSE)) -> AFG | B78: =IF(C78="","",VLOOKUP(C78,[1]ISO辞書!A:C,3,FALSE)) -> Afghanistan | C78: アフガニスタン | D78: アフガニスタンの地震被害 | E78: アフガニスタンのヒンドゥークシュ地域でマグニチュード5.9の地震が発生。首都カブールでは家屋倒壊による死者が出た。 | M78: =IF(J78="","",VLOOKUP(J78,[1]ISO辞書!A:B,2,FALSE)) | N78: =IF(K78="","",VLOOKUP(K78,[1]ISO辞書!A:B,2,FALSE)) | O78: =IF(L78="","",VLOOKUP(L78,[1]ISO辞書!A:B,2,FALSE)) | P78: =_xlfn.TEXTJOIN(";",TRUE,M78:O78) | R78: その他 | S78: 46115 | T78: Reuters | U78: https://www.reuters.com/business/environment/earthquake-magnitude-59-strikes-afghanistans-hindu-kush-region-gfz-says-2026-04-03/ | V78: 2
A79: =IF(C79="","",VLOOKUP(C79,[1]ISO辞書!A:C,2,FALSE)) -> GRC | B79: =IF(C79="","",VLOOKUP(C79,[1]ISO辞書!A:C,3,FALSE)) -> Greece | C79: ギリシャ | D79: ギリシャが内閣改造を実施 | E79: ギリシャのミツォタキス首相は、EUの農業補助金をめぐる不正疑惑の拡大を受けて内閣改造に踏み切った。 | M79: =IF(J79="","",VLOOKUP(J79,[1]ISO辞書!A:B,2,FALSE)) | N79: =IF(K79="","",VLOOKUP(K79,[1]ISO辞書!A:B,2,FALSE)) | O79: =IF(L79="","",VLOOKUP(L79,[1]ISO辞書!A:B,2,FALSE)) | P79: =_xlfn.TEXTJOIN(";",TRUE,M79:O79) | R79: 国内政治 | S79: 46115 | T79: Reuters | U79: https://www.reuters.com/business/finance/greek-pm-reshuffle-cabinet-amid-farm-fraud-scandal-over-eu-aid-2026-04-03/ | V79: 2
A80: =IF(C80="","",VLOOKUP(C80,[1]ISO辞書!A:C,2,FALSE)) -> UKR | B80: =IF(C80="","",VLOOKUP(C80,[1]ISO辞書!A:C,3,FALSE)) -> Ukraine | C80: ウクライナ | D80: ウクライナとトルコの首脳会談 | E80: ウクライナのゼレンスキー大統領はイスタンブールでエルドアン大統領と会談し、安全保障協力を強化することが合意されたほか、エネルギーと黒海航路も議題にあがった。 | J80: トルコ | M80: =IF(J80="","",VLOOKUP(J80,[1]ISO辞書!A:B,2,FALSE)) -> TUR | N80: =IF(K80="","",VLOOKUP(K80,[1]ISO辞書!A:B,2,FALSE)) | O80: =IF(L80="","",VLOOKUP(L80,[1]ISO辞書!A:B,2,FALSE)) | P80: =_xlfn.TEXTJOIN(";",TRUE,M80:O80) -> TUR | Q80: トルコとの連携が深まることでウクライナの外交・防衛の選択肢が広がり、黒海物流の見通しにも影響する。 | R80: 安全保障 | S80: 46116 | T80: Reuters | U80: https://www.reuters.com/business/aerospace-defense/zelenskiy-arrives-istanbul-talks-with-erdogan-2026-04-04/ | V80: 4
A81: =IF(C81="","",VLOOKUP(C81,[1]ISO辞書!A:C,2,FALSE)) -> IRN | B81: =IF(C81="","",VLOOKUP(C81,[1]ISO辞書!A:C,3,FALSE)) -> Iran | C81: イラン | D81: イラン政府が反体制派関係者2名を処刑と発表 | E81: イラン政府は反体制組織との関係があるとして2人を処刑した。国内メディアは、武装攻撃への関与も理由に挙げた。 | M81: =IF(J81="","",VLOOKUP(J81,[1]ISO辞書!A:B,2,FALSE)) | N81: =IF(K81="","",VLOOKUP(K81,[1]ISO辞書!A:B,2,FALSE)) | O81: =IF(L81="","",VLOOKUP(L81,[1]ISO辞書!A:B,2,FALSE)) | P81: =_xlfn.TEXTJOIN(";",TRUE,M81:O81) | Q81: 国内弾圧の強化は対外対立の長期化につながり、中東の緊張と原油市場の不安定化が継続されると想定される。 | R81: 国内政治 | S81: 46116 | T81: Reuters | U81: https://www.reuters.com/world/middle-east/iran-executes-two-linked-opposition-group-media-say-2026-04-04/ | V81: 3
A82: =IF(C82="","",VLOOKUP(C82,[1]ISO辞書!A:C,2,FALSE)) -> IND | B82: =IF(C82="","",VLOOKUP(C82,[1]ISO辞書!A:C,3,FALSE)) -> India | C82: インド | D82: インドが約7年ぶりにイラン産原油を調達 | E82: インドは7年ぶりにイラン産原油の購入を再開。ホルムズ海峡危機を受け、調達先を柔軟に見直している。 | J82: イラン | M82: =IF(J82="","",VLOOKUP(J82,[1]ISO辞書!A:B,2,FALSE)) -> IRN | N82: =IF(K82="","",VLOOKUP(K82,[1]ISO辞書!A:B,2,FALSE)) | O82: =IF(L82="","",VLOOKUP(L82,[1]ISO辞書!A:B,2,FALSE)) | P82: =_xlfn.TEXTJOIN(";",TRUE,M82:O82) -> IRN | Q82: 世界最大の人口を有するインドにて原油の調達先変更が行われれば、原油市場の需給を動かしうる要素と言える。 | R82: エネルギー | S82: 46116 | T82: Reuters | U82: https://www.reuters.com/business/energy/india-says-crude-oil-supplies-secured-no-payment-issues-iran-imports-2026-04-04/ | V82: 4
A83: =IF(C83="","",VLOOKUP(C83,[1]ISO辞書!A:C,2,FALSE)) -> COD | B83: =IF(C83="","",VLOOKUP(C83,[1]ISO辞書!A:C,3,FALSE)) -> Democratic Republic of the Congo | C83: コンゴ民主共和国 | D83: DRコンゴ、アメリカからの第三国移民受け入れへ | E83: コンゴ民主共和国は、アメリカから送られる第三国出身の移民を受け入れる新たな合意を結んだ。移民管理でアメリカとの協力が進む。 | J83: アメリカ | M83: =IF(J83="","",VLOOKUP(J83,[1]ISO辞書!A:B,2,FALSE)) -> USA | N83: =IF(K83="","",VLOOKUP(K83,[1]ISO辞書!A:B,2,FALSE)) | O83: =IF(L83="","",VLOOKUP(L83,[1]ISO辞書!A:B,2,FALSE)) | P83: =_xlfn.TEXTJOIN(";",TRUE,M83:O83) -> USA | R83: 外交 | S83: 46117 | T83: Bloomberg | U83: https://www.bloomberg.com/news/articles/2026-04-05/congo-is-latest-country-to-take-third-country-deportees-from-us?srnd=phx-politics | V83: 4
A84: =IF(C84="","",VLOOKUP(C84,[1]ISO辞書!A:C,2,FALSE)) -> IRN | B84: =IF(C84="","",VLOOKUP(C84,[1]ISO辞書!A:C,3,FALSE)) -> Iran | C84: イラン | D84: UAEの石油化学プラントがイランの攻撃を受ける | E84: UAEのボロージュ工場で複数回の火災が起き、石油精製設備の操業が停止した。 | J84: UAE | M84: =IF(J84="","",VLOOKUP(J84,[1]ISO辞書!A:B,2,FALSE)) -> ARE | N84: =IF(K84="","",VLOOKUP(K84,[1]ISO辞書!A:B,2,FALSE)) | O84: =IF(L84="","",VLOOKUP(L84,[1]ISO辞書!A:B,2,FALSE)) | P84: =_xlfn.TEXTJOIN(";",TRUE,M84:O84) -> ARE | Q84: 湾岸諸国の石油精製設備などの設備停止は、物流コストの上昇や化学品の輸入に影響がで売る。 | R84: 紛争 | S84: 46117 | T84: Bloomberg | U84: https://www.bloomberg.com/news/articles/2026-04-05/borouge-suspends-abu-dhabi-plant-operations-after-multiple-fires?srnd=phx-politics | V84: 4
A85: =IF(C85="","",VLOOKUP(C85,[1]ISO辞書!A:C,2,FALSE)) -> USA | B85: =IF(C85="","",VLOOKUP(C85,[1]ISO辞書!A:C,3,FALSE)) -> America | C85: アメリカ | D85: アメリカが故ソレイマニ将軍の姪を逮捕 | E85: 米当局は、イランの故ソレイマニ司令官の娘らを拘束した。 | J85: イラン | M85: =IF(J85="","",VLOOKUP(J85,[1]ISO辞書!A:B,2,FALSE)) -> IRN | N85: =IF(K85="","",VLOOKUP(K85,[1]ISO辞書!A:B,2,FALSE)) | O85: =IF(L85="","",VLOOKUP(L85,[1]ISO辞書!A:B,2,FALSE)) | P85: =_xlfn.TEXTJOIN(";",TRUE,M85:O85) -> IRN | Q85: 米国内で永住権を所持していたが、これがはく奪される | R85: 国内政治 | S85: 46117 | T85: Bloomberg | U85: https://www.bloomberg.com/news/articles/2026-04-04/us-arrests-niece-of-late-iranian-general-soleimani?srnd=phx-politics | V85: 3
A86: =IF(C86="","",VLOOKUP(C86,[1]ISO辞書!A:C,2,FALSE)) -> UKR | B86: =IF(C86="","",VLOOKUP(C86,[1]ISO辞書!A:C,3,FALSE)) -> Ukraine | C86: ウクライナ | D86: ウクライナのドローン攻撃でロシアの製油所に被害 | E86: ロシアのバルト海沿岸プリモルスクで、ドローン攻撃により送油管の一部が損傷した。火災は鎮火したが、原油供給への打撃は続く。 | J86: ロシア | M86: =IF(J86="","",VLOOKUP(J86,[1]ISO辞書!A:B,2,FALSE)) -> RUS | N86: =IF(K86="","",VLOOKUP(K86,[1]ISO辞書!A:B,2,FALSE)) | O86: =IF(L86="","",VLOOKUP(L86,[1]ISO辞書!A:B,2,FALSE)) | P86: =_xlfn.TEXTJOIN(";",TRUE,M86:O86) -> RUS | R86: 紛争 | S86: 46117 | T86: Reuters | U86: https://www.reuters.com/world/oil-pipeline-russias-primorsk-damaged-drone-attack-governor-says-2026-04-05/ | V86: 3
A87: =IF(C87="","",VLOOKUP(C87,[1]ISO辞書!A:C,2,FALSE)) -> UKR | B87: =IF(C87="","",VLOOKUP(C87,[1]ISO辞書!A:C,3,FALSE)) -> Ukraine | C87: ウクライナ | D87: ウクライナとシリアの首脳会談 | E87: ウクライナのゼレンスキー大統領はシリアのシャラア大統領と会談し、安全保障協力で合意した。中東歴訪の一環で、対ドローン技術の共有も議題となった。 | J87: シリア | M87: =IF(J87="","",VLOOKUP(J87,[1]ISO辞書!A:B,2,FALSE)) -> SYR | N87: =IF(K87="","",VLOOKUP(K87,[1]ISO辞書!A:B,2,FALSE)) | O87: =IF(L87="","",VLOOKUP(L87,[1]ISO辞書!A:B,2,FALSE)) | P87: =_xlfn.TEXTJOIN(";",TRUE,M87:O87) -> SYR | Q87: ウクライナの協力先が中東へ広がれば、戦争の外交地図が変わり、日本の中東外交にも影響する。 | R87: 安全保障 | S87: 46117 | T87: Reuters | U87: https://www.reuters.com/world/middle-east/zelenskiy-syria-meet-president-sharaa-sources-say-2026-04-05/ | V87: 4
A88: =IF(C88="","",VLOOKUP(C88,[1]ISO辞書!A:C,2,FALSE)) -> USA | B88: =IF(C88="","",VLOOKUP(C88,[1]ISO辞書!A:C,3,FALSE)) -> America | C88: アメリカ | D88: イラン革命防衛隊情報部門トップが死亡 | E88: イラン革命防衛隊の情報組織トップ、ハデミ氏の死亡がイラン国営メディアで伝えられた。死因や経緯は公表されていない。 | J88: イラン | M88: =IF(J88="","",VLOOKUP(J88,[1]ISO辞書!A:B,2,FALSE)) -> IRN | N88: =IF(K88="","",VLOOKUP(K88,[1]ISO辞書!A:B,2,FALSE)) | O88: =IF(L88="","",VLOOKUP(L88,[1]ISO辞書!A:B,2,FALSE)) | P88: =_xlfn.TEXTJOIN(";",TRUE,M88:O88) -> IRN | Q88: 中枢幹部の死亡は指揮系統の混乱や報復の連鎖を招き、中東危機を長引かせる。 | R88: 紛争 | S88: 46118 | T88: Reuters | U88: https://www.reuters.com/world/head-irans-revolutionary-guards-intelligence-organisation-announced-dead-state-2026-04-06/ | V88: 4
A89: =IF(C89="","",VLOOKUP(C89,[1]ISO辞書!A:C,2,FALSE)) -> IRN | B89: =IF(C89="","",VLOOKUP(C89,[1]ISO辞書!A:C,3,FALSE)) -> Iran | C89: イラン | D89: イラン、アメリカによる停戦案を拒否 | E89: イランはアメリカの停戦案を退け、戦争の一時停止ではなく恒久的な終結を求める立場を示した。ホルムズ海峡の安全確保も交渉条件に挙げた。 | J89: アメリカ | M89: =IF(J89="","",VLOOKUP(J89,[1]ISO辞書!A:B,2,FALSE)) -> USA | N89: =IF(K89="","",VLOOKUP(K89,[1]ISO辞書!A:B,2,FALSE)) | O89: =IF(L89="","",VLOOKUP(L89,[1]ISO辞書!A:B,2,FALSE)) | P89: =_xlfn.TEXTJOIN(";",TRUE,M89:O89) -> USA | Q89: 停戦がまとまらなければ海峡リスクが続き、世界はもちろん日本における原油や海運コストが高止まりしやすい。 | R89: 紛争 | S89: 46118 | T89: Reuters | U89: https://www.reuters.com/world/iran-rejects-ceasefire-response-proposals-emphasises-need-permanent-end-war-irna-2026-04-06/ | V89: 5
A90: =IF(C90="","",VLOOKUP(C90,[1]ISO辞書!A:C,2,FALSE)) -> CHN | B90: =IF(C90="","",VLOOKUP(C90,[1]ISO辞書!A:C,3,FALSE)) -> China | C90: 中国 | D90: 中国、サプライチェーン確保のための新制度を発表 | E90: 中国は、外国からの差別的な禁輸や供給網を脅かす行為に対し、政府機関が安全保障調査を始められる新規則を導入した。 | M90: =IF(J90="","",VLOOKUP(J90,[1]ISO辞書!A:B,2,FALSE)) | N90: =IF(K90="","",VLOOKUP(K90,[1]ISO辞書!A:B,2,FALSE)) | O90: =IF(L90="","",VLOOKUP(L90,[1]ISO辞書!A:B,2,FALSE)) | P90: =_xlfn.TEXTJOIN(";",TRUE,M90:O90) | Q90: 対中サプライチェーンの分断が進み、日本企業の調達先分散や法務対応の負担が増える可能性。 | R90: 経済 | S90: 46119 | T90: Bloomberg | U90: https://www.bloomberg.com/news/articles/2026-04-07/china-issues-new-supply-chain-rules-targeting-foreign-disruption?srnd=phx-politics | V90: 3
A91: =IF(C91="","",VLOOKUP(C91,[1]ISO辞書!A:C,2,FALSE)) -> PAK | B91: =IF(C91="","",VLOOKUP(C91,[1]ISO辞書!A:C,3,FALSE)) -> Pakistan | C91: パキスタン | D91: パキスタンとエジプト首脳の電話会談 | E91: パキスタンとエジプトは、米トランプ大統領が設定した期限が迫る中、イラン戦争を止めるための外交協議を急いだ。 | J91: エジプト | K91: イラン | L91: アメリカ | M91: =IF(J91="","",VLOOKUP(J91,[1]ISO辞書!A:B,2,FALSE)) -> EGY | N91: =IF(K91="","",VLOOKUP(K91,[1]ISO辞書!A:B,2,FALSE)) -> IRN | O91: =IF(L91="","",VLOOKUP(L91,[1]ISO辞書!A:B,2,FALSE)) -> USA | P91: =_xlfn.TEXTJOIN(";",TRUE,M91:O91) -> EGY;IRN;USA | Q91: 停戦外交が進めば中東の原油高圧力は和らぐが、状況は依然として不透明。 | R91: 首脳会談 | S91: 46119 | T91: Bloomberg | U91: https://www.bloomberg.com/news/articles/2026-04-07/pakistan-egypt-step-up-diplomacy-as-trump-s-iran-deadline-looms?srnd=phx-politics | V91: 4
A92: =IF(C92="","",VLOOKUP(C92,[1]ISO辞書!A:C,2,FALSE)) -> VNM | B92: =IF(C92="","",VLOOKUP(C92,[1]ISO辞書!A:C,3,FALSE)) -> Viet Nam | C92: ベトナム | D92: ベトナムにてトラム氏が大統領に就任する | E92: ベトナム国民議会はト・ラム氏を国家主席に選出し、党と国家の要職を兼ねる体制が固まった。経済停滞への対応と権力集中が同時に進んだ。 | M92: =IF(J92="","",VLOOKUP(J92,[1]ISO辞書!A:B,2,FALSE)) | N92: =IF(K92="","",VLOOKUP(K92,[1]ISO辞書!A:B,2,FALSE)) | O92: =IF(L92="","",VLOOKUP(L92,[1]ISO辞書!A:B,2,FALSE)) | P92: =_xlfn.TEXTJOIN(";",TRUE,M92:O92) | Q92: 統治の安定が進めば投資環境は改善し、日本企業にとってもベトナム戦略の見通しが立ちやすくなる。 | R92: 国内政治 | S92: 46119 | T92: Bloomberg | U92: https://www.bloomberg.com/news/articles/2026-04-07/vietnam-s-to-lam-secures-presidency-tightening-grip-on-power?srnd=phx-politics | V92: 2
A93: =IF(C93="","",VLOOKUP(C93,[1]ISO辞書!A:C,2,FALSE)) -> SSD | B93: =IF(C93="","",VLOOKUP(C93,[1]ISO辞書!A:C,3,FALSE)) -> South Sudan | C93: 南スーダン | D93: 南スーダンにて国会議長と副議長が解任される | E93: 南スーダンのキール大統領が、国民議会の議長と副議長を解任した。理由は明らかにされておらず、政権内の再編が進んでいる。 | M93: =IF(J93="","",VLOOKUP(J93,[1]ISO辞書!A:B,2,FALSE)) | N93: =IF(K93="","",VLOOKUP(K93,[1]ISO辞書!A:B,2,FALSE)) | O93: =IF(L93="","",VLOOKUP(L93,[1]ISO辞書!A:B,2,FALSE)) | P93: =_xlfn.TEXTJOIN(";",TRUE,M93:O93) | Q93: 政治の不安定化は内戦後の統治回復を遅らせ、東アフリカの安定と人道支援に影響する。 | R93: 国内政治 | S93: 46119 | T93: Reuters | U93: https://www.reuters.com/world/africa/south-sudans-kiir-sacks-parliament-speaker-deputy-2026-04-07/ | V93: 2
A94: =IF(C94="","",VLOOKUP(C94,[1]ISO辞書!A:C,2,FALSE)) -> IRN | B94: =IF(C94="","",VLOOKUP(C94,[1]ISO辞書!A:C,3,FALSE)) -> Iran | C94: イラン | D94: イランがサウジアラビアの石油コンビナートを攻撃 | E94: イラン革命防衛隊は、サウジアラビア東部ジュバイルの石油化学施設を攻撃したと発表。米・イスラエルの攻撃への報復で、ホルムズ海峡をめぐる緊張がさらに高まった。 | J94: サウジアラビア | M94: =IF(J94="","",VLOOKUP(J94,[1]ISO辞書!A:B,2,FALSE)) -> SAU | N94: =IF(K94="","",VLOOKUP(K94,[1]ISO辞書!A:B,2,FALSE)) | O94: =IF(L94="","",VLOOKUP(L94,[1]ISO辞書!A:B,2,FALSE)) | P94: =_xlfn.TEXTJOIN(";",TRUE,M94:O94) -> SAU | Q94: サウジアラビアやUAEといった国々を巻きこんだ紛争の拡大と、さらなるエネルギー調達への影響が危惧される。 | R94: 紛争 | S94: 46119 | T94: Reuters | U94: https://www.reuters.com/world/middle-east/iran-has-attacked-saudi-petrochemical-complex-jubail-fars-news-agency-says-2026-04-07/ | V94: 4
A95: =IF(C95="","",VLOOKUP(C95,[1]ISO辞書!A:C,2,FALSE)) -> USA | B95: =IF(C95="","",VLOOKUP(C95,[1]ISO辞書!A:C,3,FALSE)) -> America | C95: アメリカ | D95: アメリカがイランのハルグ島を攻撃 | E95: 米軍はイランのカーグ島にある軍事目標を攻撃したと発表。湾岸諸国での攻撃の応酬は、戦線の拡大を示している。 | J95: イラン | M95: =IF(J95="","",VLOOKUP(J95,[1]ISO辞書!A:B,2,FALSE)) -> IRN | N95: =IF(K95="","",VLOOKUP(K95,[1]ISO辞書!A:B,2,FALSE)) | O95: =IF(L95="","",VLOOKUP(L95,[1]ISO辞書!A:B,2,FALSE)) | P95: =_xlfn.TEXTJOIN(";",TRUE,M95:O95) -> IRN | Q95: 攻撃拡大はホルムズ海峡の安全を一段と不安定にし、日本の原油調達リスクを押し上げる。 | R95: 紛争 | S95: 46119 | T95: Reuters | U95: https://www.reuters.com/world/middle-east/us-strikes-military-targets-irans-kharg-island-us-official-says-2026-04-07/ | V95: 4
A96: =IF(C96="","",VLOOKUP(C96,[1]ISO辞書!A:C,2,FALSE)) -> USA | B96: =IF(C96="","",VLOOKUP(C96,[1]ISO辞書!A:C,3,FALSE)) -> America | C96: アメリカ | D96: アメリカとイランが2週間の停戦に合意 | E96: アメリカとイランは2週間の停戦で合意。パキスタンの仲介により協議が進展し、今後は同国の首都イスラマバードで本格協議に入る。 | J96: イラン | K96: パキスタン | M96: =IF(J96="","",VLOOKUP(J96,[1]ISO辞書!A:B,2,FALSE)) -> IRN | N96: =IF(K96="","",VLOOKUP(K96,[1]ISO辞書!A:B,2,FALSE)) -> PAK | O96: =IF(L96="","",VLOOKUP(L96,[1]ISO辞書!A:B,2,FALSE)) | P96: =_xlfn.TEXTJOIN(";",TRUE,M96:O96) -> IRN;PAK | Q96: 恒久的な停戦が期待されるが、協議により更なる関係悪化の可能性も残る。 | R96: 紛争 | S96: 46120 | T96: Bloomberg | U96: https://www.bloomberg.com/news/articles/2026-04-08/us-iran-ceasefire-what-s-been-agreed-will-the-strait-of-hormuz-reopen?srnd=phx-politics | V96: 5
A97: =IF(C97="","",VLOOKUP(C97,[1]ISO辞書!A:C,2,FALSE)) -> JPN | B97: =IF(C97="","",VLOOKUP(C97,[1]ISO辞書!A:C,3,FALSE)) -> Japan | C97: 日本 | D97: 日本とイラン首脳の電話会談 | E97: 日本の高市首相がイランのペゼシュキアン大統領と電話で会談。停戦の持続とホルムズ海峡の状況を協議した。 | J97: イラン | M97: =IF(J97="","",VLOOKUP(J97,[1]ISO辞書!A:B,2,FALSE)) -> IRN | N97: =IF(K97="","",VLOOKUP(K97,[1]ISO辞書!A:B,2,FALSE)) | O97: =IF(L97="","",VLOOKUP(L97,[1]ISO辞書!A:B,2,FALSE)) | P97: =_xlfn.TEXTJOIN(";",TRUE,M97:O97) -> IRN | Q97: 日本の首相が直接関与することで、原油供給と海上交通の安定を求める外交圧力が強まる。 | R97: 紛争 | S97: 46120 | T97: Bloomberg | U97: https://www.bloomberg.com/news/articles/2026-04-08/japan-s-pm-takaichi-speaks-with-iran-s-pezeshkian-reports-say?srnd=phx-politics | V97: 4
A98: =IF(C98="","",VLOOKUP(C98,[1]ISO辞書!A:C,2,FALSE)) -> MDG | B98: =IF(C98="","",VLOOKUP(C98,[1]ISO辞書!A:C,3,FALSE)) -> Madagascar | C98: マダガスカル | D98: マダガスカルにて非常事態宣言が発令 | E98: マダガスカルは、イラン情勢による燃料供給混乱を受け、15日間のエネルギー非常事態を宣言した。燃料不足への危機感が高まっている。 | M98: =IF(J98="","",VLOOKUP(J98,[1]ISO辞書!A:B,2,FALSE)) | N98: =IF(K98="","",VLOOKUP(K98,[1]ISO辞書!A:B,2,FALSE)) | O98: =IF(L98="","",VLOOKUP(L98,[1]ISO辞書!A:B,2,FALSE)) | P98: =_xlfn.TEXTJOIN(";",TRUE,M98:O98) | Q98: 燃料不足は島嶼国の経済を直撃し、海上輸送や援助の重要性が日本にも改めて突きつけられる。 | R98: 国内政治 | S98: 46120 | T98: Bloomberg | U98: https://www.bloomberg.com/news/articles/2026-04-08/madagascar-declares-state-of-emergency-over-energy-supply-woes?srnd=phx-politics | V98: 3
A99: =IF(C99="","",VLOOKUP(C99,[1]ISO辞書!A:C,2,FALSE)) -> RUS | B99: =IF(C99="","",VLOOKUP(C99,[1]ISO辞書!A:C,3,FALSE)) -> Russian Federation | C99: ロシア | D99: 中ロが国連安保理のホルムズ海峡に関する決議案に拒否権を行使 | E99: 中国とロシアは、ホルムズ海峡の商船保護を求める国連決議に拒否権を行使した。アメリカはこの動きをイランを利する判断だと反発した。 | J99: 中国 | K99: イラン | L99: アメリカ | M99: =IF(J99="","",VLOOKUP(J99,[1]ISO辞書!A:B,2,FALSE)) -> CHN | N99: =IF(K99="","",VLOOKUP(K99,[1]ISO辞書!A:B,2,FALSE)) -> IRN | O99: =IF(L99="","",VLOOKUP(L99,[1]ISO辞書!A:B,2,FALSE)) -> USA | P99: =_xlfn.TEXTJOIN(";",TRUE,M99:O99) -> CHN;IRN;USA | Q99: 安保理の足並みが乱れると海峡再開の実効策が弱まり、世界的なエネルギー不安が継続される。 | R99: 紛争 | S99: 46120 | T99: Bloomberg | U99: https://www.bloomberg.com/news/articles/2026-04-07/china-and-russia-veto-security-council-resolution-on-hormuz?srnd=phx-politics | V99: 4
A100: =IF(C100="","",VLOOKUP(C100,[1]ISO辞書!A:C,2,FALSE)) -> MEX | B100: =IF(C100="","",VLOOKUP(C100,[1]ISO辞書!A:C,3,FALSE)) -> Mexico | C100: メキシコ | D100: メキシコにて新たな外務大臣が任命される | E100: メキシコ上院は、北米担当のベラスコ氏を新外相に承認した。アメリカ・カナダとのUSMCA再検討が進む時期の交代となる。 | M100: =IF(J100="","",VLOOKUP(J100,[1]ISO辞書!A:B,2,FALSE)) | N100: =IF(K100="","",VLOOKUP(K100,[1]ISO辞書!A:B,2,FALSE)) | O100: =IF(L100="","",VLOOKUP(L100,[1]ISO辞書!A:B,2,FALSE)) | P100: =_xlfn.TEXTJOIN(";",TRUE,M100:O100) | Q100: 北米における自由貿易協定の維持に向けた動きが期待される。 | R100: 国内政治 | S100: 46120 | T100: Reuters | U100: https://www.reuters.com/world/americas/mexico-senate-confirms-north-america-diplomat-velasco-foreign-minister-2026-04-08/ | V100: 1
...
